Workbook

Sheet Cover
C3: Oil and Gas Exploration & Production Company Analysis and Valuation
C6: Table of Contents
C7: 1 | D7: Dashboard
C8: =C7+1 -> 2 | D8: Historical Financials
C9: =C8+1 -> 3 | D9: Production & Reserves
C10: =C9+1 -> 4 | D10: Capital Structure
C11: =C10+1 -> 5 | D11: Debt Schedule
C12: =C11+1 -> 6 | D12: Forcast Model
C13: =C12+1 -> 7 | D13: NAV & Valuation
C14: =C13+1 -> 8 | D14: Notes

Sheet Historical Financials
B3: Financials
B6: Income Statement
F8: 2021 | G8: 2022 | H8: 2023 | I8: 2024 | J8: 2025
B9: Revenue:
B10: Natural Gas | F10: 31708185 | G10: 56948734 | H10: 14864214 | I10: 10786068 | J10: 29121446
B11: Natural Gas Liquids | F11: 1053486 | G11: 1733130 | H11: 984418 | I11: 1481958 | J11: 1978860
B12: Oil and Condensates | F12: 1776496 | G12: 3195333 | H12: 5090589 | I12: 13730686 | J12: 13803515
B13: Gathering and Compression | F13: 7865825 | G13: 8085512 | H13: 9790531 | I13: 5524063 | J13: 6683735
B14: Total Revenue | F14: =SUM(F10:F13) -> 42403992 | G14: =SUM(G10:G13) -> 69962709 | H14: =SUM(H10:H13) -> 30729752 | I14: =SUM(I10:I13) -> 31522775 | J14: =SUM(J10:J13) -> 51587556
B16: Operating Expenses:
B17: Lease Operating Expenses | F17: 7897738 | G17: 7128631 | H17: 6405281 | I17: 7264824 | J17: 12518325
B18: Gathering System Operating Expenses | F18: 726646 | G18: 2287763 | H18: 2459694 | I18: 2265190 | J18: 2362036
B19: Development of Geological and Geophysical Expenses | F19: 40299 | G19: 9545 | H19: 0 | I19: 0 | J19: 0
B20: DD&A | F20: 6627016 | G20: 6438511 | H20: 7685084 | I20: 10185119 | J20: 12170320
B21: Impairment Expense | F21: 153058 | G21: 0 | H21: 0 | I21: 1450076 | J21: 3936669
B22: Loss (Gain) on the Sale of Oil Properties | F22: -484902 | G22: -221642 | H22: 1449871 | I22: 0 | J22: 19256530
B23: Transaction Costs | F23: 0 | G23: 0 | H23: 0 | I23: 0 | J23: 2947907
B25: General and Administration:
B26: Stock Based Compensation Expense | F26: 956084 | G26: 1021026 | H26: 1018262 | I26: 1244416 | J26: 1744917
B27: Other General and Administration Expenses | F27: 5875732 | G27: 6325412 | H27: 6293234 | I27: 5688714 | J27: 7168235
B28: Total G&A | F28: =F26+F27 -> 6831816 | G28: =G26+G27 -> 7346438 | H28: =H26+H27 -> 7311496 | I28: =I26+I27 -> 6933130 | J28: =J26+J27 -> 8913152
B30: Total Operating Expenses | F30: =SUM(F17:F27) -> 21791671 | G30: =SUM(G17:G27) -> 22989246 | H30: =SUM(H17:H27) -> 25311426 | I30: =SUM(I17:I27) -> 28098339 | J30: =SUM(J17:J27) -> 62104939
B32: Operating Income (EBIT) | F32: =F14-F30 -> 20612321 | G32: =G14-G30 -> 46973463 | H32: =H14-H30 -> 5418326 | I32: =I14-I30 -> 3424436 | J32: =J14-J30 -> -10517383
B33: EBITDA | F33: =F32+F20 -> 27239337 | G33: =G32+G20 -> 53411974 | H33: =H32+H20 -> 13103410 | I33: =I32+I20 -> 13609555 | J33: =J32+J20 -> 1652937
B34: EBITDAX | F34: =F33+F19 -> 27279636 | G34: =G33+G19 -> 53421519 | H34: =H33+H19 -> 13103410 | I34: =I33+I19 -> 13609555 | J34: =J33+J19 -> 1652937
B35: Adjusted EBITDA | F35: =F33+F22+F21+F23+F19 -> 26947792 | G35: =G33+G22+G21+G23+G19 -> 53199877 | H35: =H33+H22+H21+H23+H19 -> 14553281 | I35: =I33+I22+I21+I23+I19 -> 15059631 | J35: =J33+J22+J21+J23+J19 -> 27794043
B37: Other Income (Expense):
B38: Interest Income | F38: 38865 | G38: 452877 | H38: 1673241 | I38: 493277 | J38: 188369
B39: Interest Expense | F39: -101382 | G39: -50782 | H39: -80379 | I39: -46400 | J39: -624160
B40: Gain (Loss) On Derative Contracts, Net | F40: -4482909 | G40: 236077 | H40: 3130055 | I40: -391147 | J40: 5500486
B41: Other Income, Net | F41: 1130 | G41: -99469 | H41: 4357 | I41: 76727 | J41: 16556
B42: Total Other Income (Expense) | F42: =SUM(F38:F41) -> -4544296 | G42: =SUM(G38:G41) -> 538703 | H42: =SUM(H38:H41) -> 4727274 | I42: =SUM(I38:I41) -> 132457 | J42: =SUM(J38:J41) -> 5081251
B43: Net Income (Loss) Before Income Tax (EBT) | F43: =F42+F32 -> 16068025 | G43: =G42+G32 -> 47512166 | H43: =H42+H32 -> 10145600 | I43: =I42+I32 -> 3556893 | J43: =J42+J32 -> -5436132
B45: Income Tax (Benefit) Expense | F45: 4440508 | G45: 12157487 | H45: 3200447 | I45: 1629093 | J45: 362731
B46: Net Income | F46: =F43-F45 -> 11627517 | G46: =G43-G45 -> 35354679 | H46: =H43-H45 -> 6945153 | I46: =I43-I45 -> 1927800 | J46: =J43-J45 -> -5798863
B48: Currency Transaction Adjustments | F48: -2042 | G48: -44054 | H48: -3872 | I48: 262588 | J48: -136700
B49: Unrealized Loss on Securities | F49: 0 | G49: 0 | H49: 1598 | I49: -1598 | J49: 0
B50: Net Comprehensive Income | F50: =F46+SUM(F48:F49) -> 11625475 | G50: =G46+SUM(G48:G49) -> 35310625 | H50: =H46+SUM(H48:H49) -> 6942879 | I50: =I46+SUM(I48:I49) -> 2188790 | J50: =J46+SUM(J48:J49) -> -5935563
B53: Cash Flow Statement
F55: 2021 | G55: =F55+1 -> 2022 | H55: =G55+1 -> 2023 | I55: =H55+1 -> 2024 | J55: =I55+1 -> 2025
B57: Net Income | F57: =F46 -> 11627517 | G57: =G46 -> 35354679 | H57: =H46 -> 6945153 | I57: =I46 -> 1927800 | J57: =J46 -> -5798863
B59: Non-Cash Operating Activities:
B60: DD&A | F60: 6627016 | G60: 6438511 | H60: 7685084 | I60: 10185119 | J60: 12170320
B61: Impairment Expenses | F61: 153058 | G61: 0 | H61: 0 | I61: 1450076 | J61: 3936669
B62: Loss (Gain) on Asset Sales | F62: -484902 | G62: -221642 | H62: 1449871 | I62: 0 | J62: 19256530
B63: Derivative MTM Gain (Loss) | F63: 4482909 | G63: -236077 | H63: -3130055 | I63: 391147 | J63: -5500486
B64: Derivative Cash Settlements | F64: -4243085 | G64: -1225837 | H64: 3251890 | I64: 1196656 | J64: 1163662
B65: Stock Compensation | F65: 956084 | G65: 1021026 | H65: 1018262 | I65: 1244416 | J65: 1744917
B66: Deferred Taxes | F66: -197412 | G66: 711954 | H66: 936549 | I66: 1184634 | J66: 117008
B67: Other Non-Cash Adjustments | F67: 0 | G67: -118260 | H67: -1346330 | I67: -386629 | J67: 42910
B68: Acquisition / Business Combination Adjustments | F68: 0 | G68: 0 | H68: 0 | I68: 0 | J68: 0
B70: Changes In Working Capital:
B71: Accounts Receivable | F71: -679643 | G71: -2604455 | H71: 1185938 | I71: 171726 | J71: -1588383
B72: Prepaid Taxes / Current Assets | F72: 20000 | G72: 0 | H72: 187793 | I72: -23662 | J72: -1973348
B73: Other Assets and Liabilities | F73: 0 | G73: -58368 | H73: 126347 | I73: -17828 | J73: -10365
B74: Accounts Payable & Accrued Liabilities | F74: 646410 | G74: 1182348 | H74: -122203 | I74: -493176 | J74: -2940888
B75: Income Taxes Payable | F75: 1098425 | G75: -2238519 | H75: 0 | I75: 0 | J75: 0
B77: Net Cash from Operating Activities | F77: =SUM(F57:F75) -> 20006377 | G77: =SUM(G57:G75) -> 38005360 | H77: =SUM(H57:H75) -> 18188299 | I77: =SUM(I57:I75) -> 16830279 | J77: =SUM(J57:J75) -> 20619683
B80: Cash Flow from Investing Activities:
B82: Oil and Gas Capital Spending:
B83: Unproved Property CapEx | F83: -148862 | G83: -310211 | H83: -8136442 | I83: -4507280 | J83: -6999905
B84: Proved Property CapEx | F84: -4435945 | G84: -7562502 | H84: -10377642 | I84: -31695651 | J84: -7929773
B85: Prepaid Drilling Costs | F85: 379 | G85: 0 | H85: -1813808 | I85: 831091 | J85: 736497
B86: Total O&G CapEx | F86: =SUM(F83:F85) -> -4584428 | G86: =SUM(G83:G85) -> -7872713 | H86: =SUM(H83:H85) -> -20327892 | I86: =SUM(I83:I85) -> -35371840 | J86: =SUM(J83:J85) -> -14193181
B88: Infastructure / Other:
B89: Gathering System CapEx | F89: -297841 | G89: -184032 | H89: -82302 | I89: -341452 | J89: -465203
B90: Corporate / Other CapEx | F90: -5745 | G90: -13258 | H90: -49689 | I90: -16513 | J90: 270488
B91: Infastructure CapEx | F91: =SUM(F89:F90) -> -303586 | G91: =SUM(G89:G90) -> -197290 | H91: =SUM(H89:H90) -> -131991 | I91: =SUM(I89:I90) -> -357965 | J91: =SUM(J89:J90) -> -194715
B93: Total Capex | F93: =F86+F91 -> -4888014 | G93: =G86+G91 -> -8070003 | H93: =H86+H91 -> -20459883 | I93: =I86+I91 -> -35729805 | J93: =J86+J91 -> -14387896
B95: Free Cash Flow | F95: =F77+F93 -> 15118363 | G95: =G77+G93 -> 29935357 | H95: =H77+H93 -> -2271584 | I95: =I77+I93 -> -18899526 | J95: =J77+J93 -> 6231787
B97: Acquisitions / Divestitures:
B98: Acquisitions | F98: 0 | G98: 0 | H98: 0 | I98: 0 | J98: -49754846
B99: Asset Sale Proceeds | F99: 450000 | G99: 200000 | H99: 12498 | I99: 0 | J99: 2500000
B101: Investments:
B102: Investment Purchases | F102: 0 | G102: 0 | H102: -44801956 | I102: -4045785 | J102: 0
B103: Investment Sales / Maturities | F103: 0 | G103: 0 | H103: 26864976 | I103: 23116930 | J103: 0
B105: Net Cash from Investing Activities | F105: =F93+SUM(F98:F103) -> -4438014 | G105: =G93+SUM(G98:G103) -> -7870003 | H105: =H93+SUM(H98:H103) -> -38384365 | I105: =I93+SUM(I98:I103) -> -16658660 | J105: =J93+SUM(J98:J103) -> -61642742
B107: Cash Flow from Financing Activities:
B109: Debt Activities:
B110: Credit Facility Borrowings | F110: 0 | G110: 0 | H110: 0 | I110: 0 | J110: 50500000
B111: Debt Repayments | F111: 0 | G111: 0 | H111: 0 | I111: 0 | J111: 0
B112: Debt Issuance | F112: 0 | G112: 0 | H112: -140000 | I112: 0 | J112: 0
B114: Equity Activities:
B115: Equity Issuance / Option Exercises | F115: 85338 | G115: 747112 | H115: 62875 | I115: 0 | J115: 0
B116: Share Repurchases | F116: -2423007 | G116: -6234879 | H116: -6055601 | I116: -1831208 | J116: 0
B118: Shareholder Returns:
B119: Dividends Paid | F119: 0 | G119: -5862012 | H119: -5600655 | I119: -5486834 | J119: -5998223
B121: Other Financing:
B122: Financing Fees / Deferred Financing Costs | F122: 0 | G122: 0 | H122: 0 | I122: 0 | J122: -818857
B124: Net Cash From Financing Activities | F124: =SUM(F110:F122) -> -2337669 | G124: =SUM(G110:G122) -> -11349779 | H124: =SUM(H110:H122) -> -11733381 | I124: =SUM(I110:I122) -> -7318042 | J124: =SUM(J110:J122) -> 43682920
B127: Effects of Currency Rates on Cash | F127: -2042 | G127: -44054 | H127: -3872 | I127: 262588 | J127: -136700
B129: Cash Balance:
B130: Beginning Cash Balance | F130: 13836771 | G130: =F132 -> 27065423 | H130: =G132 -> 45806947 | I130: =H132 -> 13873628 | J130: =I132 -> 6989793
B131: Increase (Decrease) in Cash Balance | F131: =F77+F105+F124+F127 -> 13228652 | G131: =G77+G105+G124+G127 -> 18741524 | H131: =H77+H105+H124+H127 -> -31933319 | I131: =I77+I105+I124+I127 -> -6883835 | J131: =J77+J105+J124+J127 -> 2523161
B132: Ending Cash Balance | F132: =SUM(F130:F131) -> 27065423 | G132: =SUM(G130:G131) -> 45806947 | H132: =SUM(H130:H131) -> 13873628 | I132: =SUM(I130:I131) -> 6989793 | J132: =SUM(J130:J131) -> 9512954
B135: Cash, Cash Equivalents, & Restricted Cash Schedule
F137: 2021 | G137: =F137+1 -> 2022 | H137: =G137+1 -> 2023 | I137: =H137+1 -> 2024 | J137: =I137+1 -> 2025
B139: Cash & Cash Equivalents | F139: 26497305 | G139: 45236584 | H139: 13403628 | I139: 6519793 | J139: 8959954
B140: Restricted Cash | F140: =F141-F139 -> 568118 | G140: =G141-G139 -> 570363 | H140: =H141-H139 -> 470000 | I140: =I141-I139 -> 470000 | J140: =J141-J139 -> 553000
B141: Total Cash, Cash Equivalents, & Restricted Cash | F141: =F132 -> 27065423 | G141: =G132 -> 45806947 | H141: =H132 -> 13873628 | I141: =I132 -> 6989793 | J141: =J132 -> 9512954
...

Sheet Production & Reserves
B2: Production & Reserves
B4: Unit Glossary: | C4: Natural Gas: | E4: Oil: | I4: NGL
C5: Mcf | D5: Thousand Cubic Feet | E5: Bbl | F5: Barrel of Oil | I5: Boe | J5: Barrels of Oil Equivalent
C6: MMcf | D6: Million Cubic Feet | E6: MBbl | F6: Thousand Barrels (1,000)
C7: Bcf | D7: Billion Cubic Feet | E7: MMBbl | F7: Million Barrels (1,000,000)
B10: Production
F12: 2021 | G12: 2022 | H12: 2023 | I12: 2024 | J12: 2025
B13: Production: | C13: Units:
B15: Natural Gas Production (Filing) | C15: MMcf | F15: 10233 | G15: 9503 | H15: 8340 | I15: 6142 | J15: 10001
B16: Multiplier to Mcf | C16: 1000 | F16: =$C$16 -> 1000 | G16: =$C$16 -> 1000 | H16: =$C$16 -> 1000 | I16: =$C$16 -> 1000 | J16: =$C$16 -> 1000
B17: Natural Gas production (Mcf) | C17: Mcf | F17: =F15*F16 -> 10233000 | G17: =G15*G16 -> 9503000 | H17: =H15*H16 -> 8340000 | I17: =I15*I16 -> 6142000 | J17: =J15*J16 -> 10001000
B19: Oil Production (Filing) | C19: MBbl | F19: 25 | G19: 32 | H19: 65 | I19: 187 | J19: 223
B20: Oil Multiplier to Bbl | C20: 1000 | F20: =$C$20 -> 1000 | G20: =$C$20 -> 1000 | H20: =$C$20 -> 1000 | I20: =$C$20 -> 1000 | J20: =$C$20 -> 1000
B21: Oil Production (Bbl) | C21: Bbl | F21: =F19*F20 -> 25000 | G21: =G19*G20 -> 32000 | H21: =H19*H20 -> 65000 | I21: =I19*I20 -> 187000 | J21: =J19*J20 -> 223000
B23: NGL Production (Filing) | C23: Mboe | F23: 29 | G23: 44 | H23: 39 | I23: 69 | J23: 81 | L23: *2021 filing has MBbl not Mboe
B24: NGL Multiplier to Boe | C24: 1000 | F24: =$C$24 -> 1000 | G24: =$C$24 -> 1000 | H24: =$C$24 -> 1000 | I24: =$C$24 -> 1000 | J24: =$C$24 -> 1000
B25: NGL Production (Boe) | F25: =F23*F24 -> 29000 | G25: =G23*G24 -> 44000 | H25: =H23*H24 -> 39000 | I25: =I23*I24 -> 69000 | J25: =J23*J24 -> 81000
B27: Standardized Production:
B29: Natural Gas Production (Boe) | C29: Boe | F29: =F17/6 -> 1705500 | G29: =G17/6 -> 1583833.3 | H29: =H17/6 -> 1390000 | I29: =I17/6 -> 1023666.7 | J29: =J17/6 -> 1666833.3
B30: Oil Production (Boe) | C30: Boe | F30: =F21 -> 25000 | G30: =G21 -> 32000 | H30: =H21 -> 65000 | I30: =I21 -> 187000 | J30: =J21 -> 223000
B31: NGL Production (Boe) | C31: Boe | F31: =F25 -> 29000 | G31: =G25 -> 44000 | H31: =H25 -> 39000 | I31: =I25 -> 69000 | J31: =J25 -> 81000
B32: Total Production (Boe) | C32: Boe | F32: =SUM(F29:F31) -> 1759500 | G32: =SUM(G29:G31) -> 1659833.3 | H32: =SUM(H29:H31) -> 1494000 | I32: =SUM(I29:I31) -> 1279666.7 | J32: =SUM(J29:J31) -> 1970833.3
B33: Total Production (Mboe) | C33: Mboe | F33: =F32/1000 -> 1759.5 | G33: =G32/1000 -> 1659.8333 | H33: =H32/1000 -> 1494 | I33: =I32/1000 -> 1279.6667 | J33: =J32/1000 -> 1970.8333
B34: Boe / day | C34: Boe/d | F34: =F32/365 -> 4820.5479 | G34: =G32/365 -> 4547.4886 | H34: =H32/365 -> 4093.1507 | I34: =I32/365 -> 3505.9361 | J34: =J32/365 -> 5399.5434
B36: Production Mix %:
B37: Gas Production % | C37: % | F37: =F29/F32 -> 0.96930946 | G37: =G29/G32 -> 0.95421227 | H37: =H29/H32 -> 0.93038822 | I37: =I29/I32 -> 0.7999479 | J37: =J29/J32 -> 0.84575053
B38: Oil Production % | C38: % | F38: =F30/F32 -> 0.014208582 | G38: =G30/G32 -> 0.019279044 | H38: =H30/H32 -> 0.043507363 | I38: =I30/I32 -> 0.14613181 | J38: =J30/J32 -> 0.11315011
B39: NGL Production % | C39: % | F39: =F31/F32 -> 0.016481955 | G39: =G31/G32 -> 0.026508686 | H39: =H31/H32 -> 0.026104418 | I39: =I31/I32 -> 0.053920292 | J39: =J31/J32 -> 0.041099366
B41: Production Growth:
B43: Natural Gas Growth % | C43: % | F43: - | G43: =(G29/F29)-1 -> -0.071337829 | H43: =(H29/G29)-1 -> -0.12238241 | I43: =(I29/H29)-1 -> -0.26354916 | J43: =(J29/I29)-1 -> 0.62829697
B44: Oil Growth % | C44: % | F44: - | G44: =(G30/F30)-1 -> 0.28 | H44: =(H30/G30)-1 -> 1.03125 | I44: =(I30/H30)-1 -> 1.8769231 | J44: =(J30/I30)-1 -> 0.19251337
B45: NGL Growth % | C45: % | F45: - | G45: =(G31/F31)-1 -> 0.51724138 | H45: =(H31/G31)-1 -> -0.11363636 | I45: =(I31/H31)-1 -> 0.76923077 | J45: =(J31/I31)-1 -> 0.17391304
B46: Total Boe Growth % | C46: % | F46: - | G46: =(G32/F32)-1 -> -0.05664488 | H46: =(H32/G32)-1 -> -0.099909629 | I46: =(I32/H32)-1 -> -0.14346274 | J46: =(J32/I32)-1 -> 0.54011461
B48: Realized Prices:
B50: Natural Gas Realized Price ($/Mcf) | C50: $/Mcf | F50: ='Historical Financials'!F10/'Production & Reserves'!F17 -> 3.0986206 | G50: ='Historical Financials'!G10/'Production & Reserves'!G17 -> 5.9927111 | H50: ='Historical Financials'!H10/'Production & Reserves'!H17 -> 1.7822799 | I50: ='Historical Financials'!I10/'Production & Reserves'!I17 -> 1.7561166 | J50: ='Historical Financials'!J10/'Production & Reserves'!J17 -> 2.9118534
B51: Oil Realized Price ($/Bbl) | C51: $/Bbl | F51: ='Historical Financials'!F12/'Production & Reserves'!F21 -> 71.05984 | G51: ='Historical Financials'!G12/'Production & Reserves'!G21 -> 99.854156 | H51: ='Historical Financials'!H12/'Production & Reserves'!H21 -> 78.316754 | I51: ='Historical Financials'!I12/'Production & Reserves'!I21 -> 73.426128 | J51: ='Historical Financials'!J12/'Production & Reserves'!J21 -> 61.89917
B52: NGL Realized Price ($/BOE) | C52: $/Boe | F52: ='Historical Financials'!F11/'Production & Reserves'!F25 -> 36.327103 | G52: ='Historical Financials'!G11/'Production & Reserves'!G25 -> 39.389318 | H52: ='Historical Financials'!H11/'Production & Reserves'!H25 -> 25.241487 | I52: ='Historical Financials'!I11/'Production & Reserves'!I25 -> 21.477652 | J52: ='Historical Financials'!J11/'Production & Reserves'!J25 -> 24.43037
B53: Total Revenue / BOE | C53: $/Boe | D53: Hydrocarbons Only | F53: =SUM('Historical Financials'!F10:F12)/'Production & Reserves'!F32 -> 19.629535 | G53: =SUM('Historical Financials'!G10:G12)/'Production & Reserves'!G32 -> 37.279163 | H53: =SUM('Historical Financials'!H10:H12)/'Production & Reserves'!H32 -> 14.015543 | I53: =SUM('Historical Financials'!I10:I12)/'Production & Reserves'!I32 -> 20.316785 | J53: =SUM('Historical Financials'!J10:J12)/'Production & Reserves'!J32 -> 22.78418
B55: Unit Economics:
B57: Total Revenue / Total Boe | C57: $/Boe | D57: Hydrocarbons Only | F57: =F53 -> 19.629535 | G57: =G53 -> 37.279163 | H57: =H53 -> 14.015543 | I57: =I53 -> 20.316785 | J57: =J53 -> 22.78418
B58: Lease Operating Expense / Total Boe | C58: $/Boe | D58: Are the wells cheap to operate? | F58: ='Historical Financials'!F17/'Production & Reserves'!F32 -> 4.4886263 | G58: ='Historical Financials'!G17/'Production & Reserves'!G32 -> 4.2947872 | H58: ='Historical Financials'!H17/'Production & Reserves'!H32 -> 4.2873367 | I58: ='Historical Financials'!I17/'Production & Reserves'!I32 -> 5.6771222 | J58: ='Historical Financials'!J17/'Production & Reserves'!J32 -> 6.3517928
B59: G&A Expense / Total Boe | C59: $/Boe | D59: Is management running a lean company? | F59: ='Historical Financials'!F28/'Production & Reserves'!F32 -> 3.8828167 | G59: ='Historical Financials'!G28/'Production & Reserves'!G32 -> 4.4260094 | H59: ='Historical Financials'!H28/'Production & Reserves'!H32 -> 4.8939063 | I59: ='Historical Financials'!I28/'Production & Reserves'!I32 -> 5.4179187 | J59: ='Historical Financials'!J28/'Production & Reserves'!J32 -> 4.5225296
B60: DD&A / Total Boe | C60: $/Boe | D60: How much capital is being depleted for each barrel produced? | F60: ='Historical Financials'!F20/'Production & Reserves'!F32 -> 3.76642 | G60: ='Historical Financials'!G20/'Production & Reserves'!G32 -> 3.8790105 | H60: ='Historical Financials'!H20/'Production & Reserves'!H32 -> 5.1439652 | I60: ='Historical Financials'!I20/'Production & Reserves'!I32 -> 7.9591969 | J60: ='Historical Financials'!J20/'Production & Reserves'!J32 -> 6.1752152
B61: EBITDAX / Total Boe | C61: $/Boe | D61: How much cash operating profit does each barrel generate? | F61: ='Historical Financials'!F34/'Production & Reserves'!F32 -> 15.504198 | G61: ='Historical Financials'!G34/'Production & Reserves'!G32 -> 32.184869 | H61: ='Historical Financials'!H34/'Production & Reserves'!H32 -> 8.7706894 | I61: ='Historical Financials'!I34/'Production & Reserves'!I32 -> 10.635234 | J61: ='Historical Financials'!J34/'Production & Reserves'!J32 -> 0.83869953
B62: FCF / Total Boe | C62: $/Boe | D62: How much free cash flow does each barrel generate? | F62: =('Historical Financials'!F77+'Historical Financials'!F93)/'Production & Reserves'!F32 -> 8.59242 | G62: =('Historical Financials'!G77+'Historical Financials'!G93)/'Production & Reserves'!G32 -> 18.035158 | H62: =('Historical Financials'!H77+'Historical Financials'!H93)/'Production & Reserves'!H32 -> -1.5204712 | I62: =('Historical Financials'!I77+'Historical Financials'!I93)/'Production & Reserves'!I32 -> -14.769101 | J62: =('Historical Financials'!J77+'Historical Financials'!J93)/'Production & Reserves'!J32 -> 3.1620061
B65: Reserves
F67: 2021 | G67: 2022 | H67: 2023 | I67: 2024 | J67: 2025
B69: Total Reserves:
C70: Units:
B71: Natural Gas Reserves (Filing) | C71: MMcf | F71: 110969 | G71: 90040 | H71: 65915 | I71: 69401 | J71: 86372
B72: Multiplier to Mcf | C72: 1000 | F72: =$C$72 -> 1000 | G72: =$C$72 -> 1000 | H72: =$C$72 -> 1000 | I72: =$C$72 -> 1000 | J72: =$C$72 -> 1000
B73: Natural Gas Reserves (Mcf) | C73: Mcf | F73: =F71*F72 -> 110969000 | G73: =G71*G72 -> 90040000 | H73: =H71*H72 -> 65915000 | I73: =I71*I72 -> 69401000 | J73: =J71*J72 -> 86372000
B75: Oil Reserves (Filing) | C75: MBbl | F75: 305 | G75: 211 | H75: 341 | I75: 1572 | J75: 9259
B76: Oil Multiplier to Bbl | C76: 1000 | F76: =$C$76 -> 1000 | G76: =$C$76 -> 1000 | H76: =$C$76 -> 1000 | I76: =$C$76 -> 1000 | J76: =$C$76 -> 1000
B77: Oil Reserves (Bbl) | C77: Bbl | F77: =F75*F76 -> 305000 | G77: =G75*G76 -> 211000 | H77: =H75*H76 -> 341000 | I77: =I75*I76 -> 1572000 | J77: =J75*J76 -> 9259000
B79: NGL Reserves (Filing) | C79: MBbl | F79: 820 | G79: 491 | H79: 383 | I79: 877 | J79: 2352
B80: NGL Multiplier to Bbl | C80: 1000 | F80: =$C$80 -> 1000 | G80: =$C$80 -> 1000 | H80: =$C$80 -> 1000 | I80: =$C$80 -> 1000 | J80: =$C$80 -> 1000
B81: NGL Reserves (Bbl) | C81: Bbl | F81: =F79*F80 -> 820000 | G81: =G79*G80 -> 491000 | H81: =H79*H80 -> 383000 | I81: =I79*I80 -> 877000 | J81: =J79*J80 -> 2352000
B83: Reserve Standardization:
B85: Natural Gas Reserves (Boe) | C85: Boe | F85: =F73/6 -> 18494833 | G85: =G73/6 -> 15006667 | H85: =H73/6 -> 10985833 | I85: =I73/6 -> 11566833 | J85: =J73/6 -> 14395333
B86: Oil Reserves (Boe) | C86: Boe | F86: =F77 -> 305000 | G86: =G77 -> 211000 | H86: =H77 -> 341000 | I86: =I77 -> 1572000 | J86: =J77 -> 9259000
B87: NGL Reserves (Boe) | C87: Boe | F87: =F81 -> 820000 | G87: =G81 -> 491000 | H87: =H81 -> 383000 | I87: =I81 -> 877000 | J87: =J81 -> 2352000
B88: Total Reserves (Boe) | C88: Boe | F88: =SUM(F85:F87) -> 19619833 | G88: =SUM(G85:G87) -> 15708667 | H88: =SUM(H85:H87) -> 11709833 | I88: =SUM(I85:I87) -> 14015833 | J88: =SUM(J85:J87) -> 26006333
B89: Total Reserves (Mboe) | C89: Mboe | F89: =F88/1000 -> 19619.833 | G89: =G88/1000 -> 15708.667 | H89: =H88/1000 -> 11709.833 | I89: =I88/1000 -> 14015.833 | J89: =J88/1000 -> 26006.333
B91: Reserves Mix %:
B92: Gas Reserves % | C92: % | F92: =F85/F88 -> 0.94266006 | G92: =G85/G88 -> 0.95531129 | H92: =H85/H88 -> 0.93817162 | I92: =I85/I88 -> 0.82526904 | J92: =J85/J88 -> 0.55353183
B93: Oil Reserves % | C93: % | F93: =F86/F88 -> 0.015545494 | G93: =G86/G88 -> 0.013432076 | H93: =H86/H88 -> 0.029120824 | I93: =I86/I88 -> 0.11215887 | J93: =J86/J88 -> 0.35602866
B94: NGL Reserves % | C94: % | F94: =F87/F88 -> 0.041794443 | G94: =G87/G88 -> 0.031256631 | H94: =H87/H88 -> 0.032707553 | I94: =I87/I88 -> 0.062572091 | J94: =J87/J88 -> 0.090439508
B96: Reserve Types:
B98: Proved Developed (PD): | C98: Units:
B100: Proved Developed Gas Reserves (Filing) | C100: MMcf | F100: 72226 | G100: 78966 | H100: 47555 | I100: 56851 | J100: 75849
B101: Multiplier to Mcf | C101: 1000 | F101: =$C101 -> 1000 | G101: =$C101 -> 1000 | H101: =$C101 -> 1000 | I101: =$C101 -> 1000 | J101: =$C101 -> 1000
B102: Proved Developed Gas Reserves (Mcf) | C102: Mcf | F102: =F100*F101 -> 72226000 | G102: =G100*G101 -> 78966000 | H102: =H100*H101 -> 47555000 | I102: =I100*I101 -> 56851000 | J102: =J100*J101 -> 75849000
B104: Proved Developed Oil Reserves (Filing) | C104: MBbl | F104: 66 | G104: 107 | H104: 272 | I104: 847 | J104: 4000
B105: Multiplier to Bbl | C105: 1000 | F105: =$C105 -> 1000 | G105: =$C105 -> 1000 | H105: =$C105 -> 1000 | I105: =$C105 -> 1000 | J105: =$C105 -> 1000
B106: Proved Developed Oil Reserves (Bbl) | C106: Bbl | F106: =F104*F105 -> 66000 | G106: =G104*G105 -> 107000 | H106: =H104*H105 -> 272000 | I106: =I104*I105 -> 847000 | J106: =J104*J105 -> 4000000
B108: Proved Developed NGL Reserves (Filing) | C108: MBbl | F108: 157 | G108: 198 | H108: 249 | I108: 490 | J108: 1599
B109: Multiplier to Bbl | C109: 1000 | F109: =$C109 -> 1000 | G109: =$C109 -> 1000 | H109: =$C109 -> 1000 | I109: =$C109 -> 1000 | J109: =$C109 -> 1000
B110: Proved Developed NGL Reserves (Bbl) | C110: Bbl | F110: =F108*F109 -> 157000 | G110: =G108*G109 -> 198000 | H110: =H108*H109 -> 249000 | I110: =I108*I109 -> 490000 | J110: =J108*J109 -> 1599000
B112: Proved Undeveloped (PUD): | C112: Units:
B114: Proved Undeveloped Gas Reserves (Filing) | C114: MMcf | F114: 38743 | G114: 11074 | H114: 18361 | I114: 12550 | J114: 10523
B115: Multiplier to Mcf | C115: 1000 | F115: =$C115 -> 1000 | G115: =$C115 -> 1000 | H115: =$C115 -> 1000 | I115: =$C115 -> 1000 | J115: =$C115 -> 1000
B116: Proved Undeveloped Gas Reserves (Mcf) | C116: Mcf | F116: =F114*F115 -> 38743000 | G116: =G114*G115 -> 11074000 | H116: =H114*H115 -> 18361000 | I116: =I114*I115 -> 12550000 | J116: =J114*J115 -> 10523000
B118: Proved Undeveloped Oil Reserves (Filing) | C118: MBbl | F118: 239 | G118: 104 | H118: 69 | I118: 725 | J118: 5259
B119: Multiplier to Bbl | C119: 1000 | F119: =$C119 -> 1000 | G119: =$C119 -> 1000 | H119: =$C119 -> 1000 | I119: =$C119 -> 1000 | J119: =$C119 -> 1000
B120: Proved Undeveloped Oil Reserves (Bbl) | C120: Bbl | F120: =F118*F119 -> 239000 | G120: =G118*G119 -> 104000 | H120: =H118*H119 -> 69000 | I120: =I118*I119 -> 725000 | J120: =J118*J119 -> 5259000
B122: Proved Undeveloped NGL Reserves (Filing) | C122: MBbl | F122: 663 | G122: 293 | H122: 134 | I122: 387 | J122: 753
B123: Multiplier to Bbl | C123: 1000 | F123: =$C123 -> 1000 | G123: =$C123 -> 1000 | H123: =$C123 -> 1000 | I123: =$C123 -> 1000 | J123: =$C123 -> 1000
B124: Proved Undeveloped NGL Reserves (Bbl) | C124: Bbl | F124: =F122*F123 -> 663000 | G124: =G122*G123 -> 293000 | H124: =H122*H123 -> 134000 | I124: =I122*I123 -> 387000 | J124: =J122*J123 -> 753000
B127: Reserve Standardization (Boe): | C127: Units:
B129: Proved Developed (PD):
B130: PD Gas Reserves | C130: Boe | F130: =F102/6 -> 12037667 | G130: =G102/6 -> 13161000 | H130: =H102/6 -> 7925833.3 | I130: =I102/6 -> 9475166.7 | J130: =J102/6 -> 12641500
B131: PD Oil Reserves | C131: Boe | F131: =F106 -> 66000 | G131: =G106 -> 107000 | H131: =H106 -> 272000 | I131: =I106 -> 847000 | J131: =J106 -> 4000000
B132: PD NGL Reserves | C132: Boe | F132: =F110 -> 157000 | G132: =G110 -> 198000 | H132: =H110 -> 249000 | I132: =I110 -> 490000 | J132: =J110 -> 1599000
B133: Total PD Reserves | C133: Boe | F133: =SUM(F130:F132) -> 12260667 | G133: =SUM(G130:G132) -> 13466000 | H133: =SUM(H130:H132) -> 8446833.3 | I133: =SUM(I130:I132) -> 10812167 | J133: =SUM(J130:J132) -> 18240500
B135: Proved Undeveloped (PUD):
B136: PUD Gas Reserves | C136: Boe | F136: =F116/6 -> 6457166.7 | G136: =G116/6 -> 1845666.7 | H136: =H116/6 -> 3060166.7 | I136: =I116/6 -> 2091666.7 | J136: =J116/6 -> 1753833.3
B137: PUD Oil Reserves | C137: Boe | F137: =F120 -> 239000 | G137: =G120 -> 104000 | H137: =H120 -> 69000 | I137: =I120 -> 725000 | J137: =J120 -> 5259000
B138: PUD NGL Reserves | C138: Boe | F138: =F124 -> 663000 | G138: =G124 -> 293000 | H138: =H124 -> 134000 | I138: =I124 -> 387000 | J138: =J124 -> 753000
B139: Total PUD Reserves | C139: Boe | F139: =SUM(F136:F138) -> 7359166.7 | G139: =SUM(G136:G138) -> 2242666.7 | H139: =SUM(H136:H138) -> 3263166.7 | I139: =SUM(I136:I138) -> 3203666.7 | J139: =SUM(J136:J138) -> 7765833.3
...

Sheet Capital Structure
B2: Capital Structure
B5: Equity
B7: Share Price | E7: 5.28 | G7: Market Capitalization | J7: =E7*E11 -> 1.5966709e+08
B8: Most Recent Filing | E8: 2026 Q1 10-Q | G8: Market Capitalization Diluted | J8: =E7*E16 -> 1.6379496e+08
B10: Shares:
B11: Basic Shares Outstanding | E11: 30239980
B12: RSUs / Restricted Shares | E12: 781792
B13: Options Outstanding | E13: 0
B14: Warrants | E14: 0
B15: Convertible Securities | E15: 0 | F15: * Do not double count convertible securities and convertible debt in enterprise value
B16: Fully Diluted Shares | E16: =E11+E12+E13+E14+E15 -> 31021772
B17: Dilution % | E17: =(E16/E11)-1 -> 0.025852927
B21: Debt & Liquidity
B23: Debt: | G23: Cash:
B24: Revolving Credit Facility | E24: 45500000 | G24: Cash & Cash Equivalents | J24: 7912858
B25: Term Loans | E25: 0 | G25: Restricted Cash | J25: 553000
B26: Senior Notes | E26: 0 | G26: Total Cash | J26: =SUM(J24:J25) -> 8465858
B27: Convertible Debt | E27: 0
B28: Other Debt | E28: 0 | G28: Net Debt | J28: =E29-J26 -> 37034142
B29: Total Debt | E29: =SUM(E24:E28) -> 45500000
B32: Enterprise Value
B34: Market Capitalization (Diluted) | E34: =J8 -> 1.6379496e+08 | G34: Enterprise Value | J34: =E34+SUM(E36:E38)-SUM(E40:E41) -> 2.008291e+08
B36: Total Debt | E36: =E29 -> 45500000
B37: Preferred Equity | E37: 0
B38: Minority Interest (Non-Controlling Interest) | E38: 0
B40: Total Cash | E40: =J26 -> 8465858
B41: Short Term Investments | E41: 0

Sheet Debt Schedule
B2: Debt Schedule
B5: Debt Summary
F7: 2021 | G7: 2022 | H7: 2023 | I7: 2024 | J7: 2025
B9: Debt Instruments:
B11: Revolving Credit Facility | F11: 0 | G11: 0 | H11: 0 | I11: 0 | J11: 50500000
B12: Terms Loans | F12: 0 | G12: 0 | H12: 0 | I12: 0 | J12: 0
B13: Senior Notes | F13: 0 | G13: 0 | H13: 0 | I13: 0 | J13: 0
B14: Convertible Debt | F14: 0 | G14: 0 | H14: 0 | I14: 0 | J14: 0
B15: Finance Leases | F15: 0 | G15: 0 | H15: 0 | I15: 0 | J15: 0
B16: Other Debt | F16: 0 | G16: 0 | H16: 0 | I16: 0 | J16: 0
B17: Total Debt | F17: =SUM(F11:F16) -> 0 | G17: =SUM(G11:G16) -> 0 | H17: =SUM(H11:H16) -> 0 | I17: =SUM(I11:I16) -> 0 | J17: =SUM(J11:J16) -> 50500000
B19: Liquidity:
B21: Total Debt | F21: =F17 -> 0 | G21: =G17 -> 0 | H21: =H17 -> 0 | I21: =I17 -> 0 | J21: =J17 -> 50500000
B22: Cash & Cash Equivalents | F22: ='Historical Financials'!F149 -> 26497305 | G22: ='Historical Financials'!G149 -> 45236584 | H22: ='Historical Financials'!H149 -> 13403628 | I22: ='Historical Financials'!I149 -> 6519793 | J22: ='Historical Financials'!J149 -> 8959954
B23: Net Debt | F23: =F21-F22 -> -26497305 | G23: =G21-G22 -> -45236584 | H23: =H21-H22 -> -13403628 | I23: =I21-I22 -> -6519793 | J23: =J21-J22 -> 41540046
B24: Adjusted EBITDA | F24: ='Historical Financials'!F35 -> 26947792 | G24: ='Historical Financials'!G35 -> 53199877 | H24: ='Historical Financials'!H35 -> 14553281 | I24: ='Historical Financials'!I35 -> 15059631 | J24: ='Historical Financials'!J35 -> 27794043
B26: Debt Metrics:
B28: Debt / Adjusted EBITDA | F28: 0 | G28: =G21/G24 -> 0 | H28: =H21/H24 -> 0 | I28: =I21/I24 -> 0 | J28: =J21/J24 -> 1.8169361 | L28: If 100% of adj. EBITDA went to debt payments, it'd take X years to repay.
B29: Net Debt / Adjusted EBITDA | F29: =F23/F24 -> -0.98328297 | G29: =G23/G24 -> -0.8503137 | H29: =H23/H24 -> -0.92100386 | I29: =I23/I24 -> -0.43293179 | J29: =J23/J24 -> 1.4945665 | L29: Negative means net cash company. Not leveraged
B30: Interest Expense | F30: =ABS('Historical Financials'!F39) -> 101382 | G30: =ABS('Historical Financials'!G39) -> 50782 | H30: =ABS('Historical Financials'!H39) -> 80379 | I30: =ABS('Historical Financials'!I39) -> 46400 | J30: =ABS('Historical Financials'!J39) -> 624160 | L30: Annual cost of debt.
B31: Adjusted EBITDA / Interest Expense | F31: =F24/F30 -> 265.8045 | G31: =G24/G30 -> 1047.6129 | H31: =H24/H30 -> 181.05825 | I31: =I24/I30 -> 324.56101 | J31: =J24/J30 -> 44.530318 | L31: How many times over can EBITDA cover interest.
B34: Debt Details
B37: Debt Instrument Type:
E38: Crrent Balance | F38: Interest Rates | G38: Maturity Date
B39: Revolving Credit Facility
B40: Term Loan A
B41: Term Loan B
B42: Senior Note A
B43: Senior Note B
B44: Senior Note C
B45: Convertible Notes
B46: Finance Leases
B47: Total Debt

Sheet Forecast Model
B2: Forcast Model
B4: Scenario | C4: 2
E5: 2026 | F5: =E5+1 -> 2027 | G5: =F5+1 -> 2028 | H5: =G5+1 -> 2029 | I5: =H5+1 -> 2030
B7: Natural Gas Growth %:
B8: Bear | E8: -0.05 | F8: -0.05 | G8: -0.05 | H8: -0.05 | I8: -0.05
B9: Base | E9: 0.05 | F9: =E9-0.01 -> 0.04 | G9: =F9-0.01 -> 0.03 | H9: =G9-0.01 -> 0.02 | I9: =H9-0.01 -> 0.01
B10: Bull | E10: 0.1 | F10: 0.1 | G10: 0.1 | H10: 0.1 | I10: 0.1
B12: Oil Growth %:
B13: Bear | E13: -0.05 | F13: -0.05 | G13: -0.05 | H13: -0.05 | I13: -0.05
B14: Base | E14: 0.05 | F14: =E14-0.01 -> 0.04 | G14: =F14-0.01 -> 0.03 | H14: =G14-0.01 -> 0.02 | I14: =H14-0.01 -> 0.01
B15: Bull | E15: 0.1 | F15: 0.1 | G15: 0.1 | H15: 0.1 | I15: 0.1
B17: NGL Growth %:
B18: Bear | E18: -0.05 | F18: -0.05 | G18: -0.05 | H18: -0.05 | I18: -0.05
B19: Base | E19: 0.05 | F19: =E19-0.01 -> 0.04 | G19: =F19-0.01 -> 0.03 | H19: =G19-0.01 -> 0.02 | I19: =H19-0.01 -> 0.01
B20: Bull | E20: 0.1 | F20: 0.1 | G20: 0.1 | H20: 0.1 | I20: 0.1
B22: Natural Gas ($Mcf):
B23: Bear | E23: 2.5 | F23: 2.5 | G23: 2.5 | H23: 2.5 | I23: 2.5
B24: Base | E24: 3.5 | F24: 3.5 | G24: 3.5 | H24: 3.5 | I24: 3.5
B25: Bull | E25: 5 | F25: 5 | G25: 5 | H25: 5 | I25: 5
B27: Oil ($/Bbl):
B28: Bear | E28: 55 | F28: 55 | G28: 55 | H28: 55 | I28: 55
B29: Base | E29: 70 | F29: 70 | G29: 70 | H29: 70 | I29: 70
B30: Bull | E30: 85 | F30: 85 | G30: 85 | H30: 85 | I30: 85
B32: NGL ($/Bbl):
B33: Bear | E33: 18 | F33: 18 | G33: 18 | H33: 18 | I33: 18
B34: Base | E34: 25 | F34: 25 | G34: 25 | H34: 25 | I34: 25
B35: Bull | E35: 35 | F35: 35 | G35: 35 | H35: 35 | I35: 35
B37: Active Assumption:
B39: Gas Growth % | E39: {=INDEX(E8:E10,$C$4)} -> 0.05 | F39: {=INDEX(F8:F10,$C$4)} -> 0.04 | G39: {=INDEX(G8:G10,$C$4)} -> 0.03 | H39: {=INDEX(H8:H10,$C$4)} -> 0.02 | I39: {=INDEX(I8:I10,$C$4)} -> 0.01
B40: Oil Growth % | E40: {=INDEX(E13:E15,$C$4)} -> 0.05 | F40: {=INDEX(F13:F15,$C$4)} -> 0.04 | G40: {=INDEX(G13:G15,$C$4)} -> 0.03 | H40: {=INDEX(H13:H15,$C$4)} -> 0.02 | I40: {=INDEX(I13:I15,$C$4)} -> 0.01
B41: NGL Growth % | E41: {=INDEX(E18:E20,$C$4)} -> 0.05 | F41: {=INDEX(F18:F20,$C$4)} -> 0.04 | G41: {=INDEX(G18:G20,$C$4)} -> 0.03 | H41: {=INDEX(H18:H20,$C$4)} -> 0.02 | I41: {=INDEX(I18:I20,$C$4)} -> 0.01
B42: Natural Gas Price ($/Mcf) | E42: {=INDEX(E23:E25,$C$4)} -> 3.5 | F42: {=INDEX(F23:F25,$C$4)} -> 3.5 | G42: {=INDEX(G23:G25,$C$4)} -> 3.5 | H42: {=INDEX(H23:H25,$C$4)} -> 3.5 | I42: {=INDEX(I23:I25,$C$4)} -> 3.5
B43: Oil Price ($/Bbl) | E43: {=INDEX(E28:E30,$C$4)} -> 70 | F43: {=INDEX(F28:F30,$C$4)} -> 70 | G43: {=INDEX(G28:G30,$C$4)} -> 70 | H43: {=INDEX(H28:H30,$C$4)} -> 70 | I43: {=INDEX(I28:I30,$C$4)} -> 70
B44: NGL Price ($/Bbl) | E44: {=INDEX(E33:E35,$C$4)} -> 25 | F44: {=INDEX(F33:F35,$C$4)} -> 25 | G44: {=INDEX(G33:G35,$C$4)} -> 25 | H44: {=INDEX(H33:H35,$C$4)} -> 25 | I44: {=INDEX(I33:I35,$C$4)} -> 25
B47: Production Forecast
F49: 2021 | G49: =F49+1 -> 2022 | H49: =G49+1 -> 2023 | I49: =H49+1 -> 2024 | J49: =I49+1 -> 2025 | K49: =J49+1 -> 2026 | L49: =K49+1 -> 2027 | M49: =L49+1 -> 2028 | N49: =M49+1 -> 2029 | O49: =N49+1 -> 2030
B51: Production: | D51: Actuals | E51: Assumptons
B53: Natural Gas Production (Mcf) | F53: ='Production & Reserves'!F17 -> 10233000 | G53: ='Production & Reserves'!G17 -> 9503000 | H53: ='Production & Reserves'!H17 -> 8340000 | I53: ='Production & Reserves'!I17 -> 6142000 | J53: ='Production & Reserves'!J17 -> 10001000 | K53: =J53*(1+K54) -> 10501050 | L53: =K53*(1+L54) -> 10921092 | M53: =L53*(1+M54) -> 11248725 | N53: =M53*(1+N54) -> 11473699 | O53: =N53*(1+O54) -> 11588436
B54: Natural Gas Production Growth % | G54: =(G53/F53)-1 -> -0.071337829 | H54: =(H53/G53)-1 -> -0.12238241 | I54: =(I53/H53)-1 -> -0.26354916 | J54: =(J53/I53)-1 -> 0.62829697 | K54: =E39 -> 0.05 | L54: =F39 -> 0.04 | M54: =G39 -> 0.03 | N54: =H39 -> 0.02 | O54: =I39 -> 0.01
B56: Oil Production (Bbl) | F56: ='Production & Reserves'!F21 -> 25000 | G56: ='Production & Reserves'!G21 -> 32000 | H56: ='Production & Reserves'!H21 -> 65000 | I56: ='Production & Reserves'!I21 -> 187000 | J56: ='Production & Reserves'!J21 -> 223000 | K56: =J56*(1+K57) -> 234150 | L56: =K56*(1+L57) -> 243516 | M56: =L56*(1+M57) -> 250821.48 | N56: =M56*(1+N57) -> 255837.91 | O56: =N56*(1+O57) -> 258396.29
B57: Oil Production Growth % | G57: =(G56/F56)-1 -> 0.28 | H57: =(H56/G56)-1 -> 1.03125 | I57: =(I56/H56)-1 -> 1.8769231 | J57: =(J56/I56)-1 -> 0.19251337 | K57: =E40 -> 0.05 | L57: =F40 -> 0.04 | M57: =G40 -> 0.03 | N57: =H40 -> 0.02 | O57: =I40 -> 0.01
B59: NGL Production (Bbl) | F59: ='Production & Reserves'!F25 -> 29000 | G59: ='Production & Reserves'!G25 -> 44000 | H59: ='Production & Reserves'!H25 -> 39000 | I59: ='Production & Reserves'!I25 -> 69000 | J59: ='Production & Reserves'!J25 -> 81000 | K59: =J59*(1+K60) -> 85050 | L59: =K59*(1+L60) -> 88452 | M59: =L59*(1+M60) -> 91105.56 | N59: =M59*(1+N60) -> 92927.671 | O59: =N59*(1+O60) -> 93856.948
B60: NGL Production Growth % | G60: =(G59/F59)-1 -> 0.51724138 | H60: =(H59/G59)-1 -> -0.11363636 | I60: =(I59/H59)-1 -> 0.76923077 | J60: =(J59/I59)-1 -> 0.17391304 | K60: =E41 -> 0.05 | L60: =F41 -> 0.04 | M60: =G41 -> 0.03 | N60: =H41 -> 0.02 | O60: =I41 -> 0.01
B62: Total Production (Boe) | F62: ='Production & Reserves'!F32 -> 1759500 | G62: ='Production & Reserves'!G32 -> 1659833.3 | H62: ='Production & Reserves'!H32 -> 1494000 | I62: ='Production & Reserves'!I32 -> 1279666.7 | J62: ='Production & Reserves'!J32 -> 1970833.3 | K62: =(K53/6)+K56+K59 -> 2069375 | L62: =(L53/6)+L56+L59 -> 2152150 | M62: =(M53/6)+M56+M59 -> 2216714.5 | N62: =(N53/6)+N56+N59 -> 2261048.8 | O62: =(O53/6)+O56+O59 -> 2283659.3
B63: Total Production (Mboe) | F63: ='Production & Reserves'!F33 -> 1759.5 | G63: ='Production & Reserves'!G33 -> 1659.8333 | H63: ='Production & Reserves'!H33 -> 1494 | I63: ='Production & Reserves'!I33 -> 1279.6667 | J63: ='Production & Reserves'!J33 -> 1970.8333 | K63: =K62/1000 -> 2069.375 | L63: =L62/1000 -> 2152.15 | M63: =M62/1000 -> 2216.7145 | N63: =N62/1000 -> 2261.0488 | O63: =O62/1000 -> 2283.6593
B64: Total Production Growth % | G64: =(G62/F62)-1 -> -0.05664488 | H64: =(H62/G62)-1 -> -0.099909629 | I64: =(I62/H62)-1 -> -0.14346274 | J64: =(J62/I62)-1 -> 0.54011461 | K64: =(K62/J62)-1 -> 0.05 | L64: =(L62/K62)-1 -> 0.04 | M64: =(M62/L62)-1 -> 0.03 | N64: =(N62/M62)-1 -> 0.02 | O64: =(O62/N62)-1 -> 0.01
B67: Revenue Forecast
F69: 2021 | G69: =F69+1 -> 2022 | H69: =G69+1 -> 2023 | I69: =H69+1 -> 2024 | J69: =I69+1 -> 2025 | K69: =J69+1 -> 2026 | L69: =K69+1 -> 2027 | M69: =L69+1 -> 2028 | N69: =M69+1 -> 2029 | O69: =N69+1 -> 2030
B71: Revenue:
B73: Natural Gas | F73: ='Historical Financials'!F10 -> 31708185 | G73: ='Historical Financials'!G10 -> 56948734 | H73: ='Historical Financials'!H10 -> 14864214 | I73: ='Historical Financials'!I10 -> 10786068 | J73: ='Historical Financials'!J10 -> 29121446 | K73: =K53*E42 -> 36753675 | L73: =L53*F42 -> 38223822 | M73: =M53*G42 -> 39370537 | N73: =N53*H42 -> 40157947 | O73: =O53*I42 -> 40559527
B74: Natural Gas Growth % | G74: =(G73/F73)-1 -> 0.79602629 | H74: =(H73/G73)-1 -> -0.73898956 | I74: =(I73/H73)-1 -> -0.27436002 | J74: =(J73/I73)-1 -> 1.6999131 | K74: =(K73/J73)-1 -> 0.26208276 | L74: =(L73/K73)-1 -> 0.04 | M74: =(M73/L73)-1 -> 0.03 | N74: =(N73/M73)-1 -> 0.02 | O74: =(O73/N73)-1 -> 0.01
B76: Oil | F76: ='Historical Financials'!F12 -> 1776496 | G76: ='Historical Financials'!G12 -> 3195333 | H76: ='Historical Financials'!H12 -> 5090589 | I76: ='Historical Financials'!I12 -> 13730686 | J76: ='Historical Financials'!J12 -> 13803515 | K76: =K56*E43 -> 16390500 | L76: =L56*F43 -> 17046120 | M76: =M56*G43 -> 17557504 | N76: =N56*H43 -> 17908654 | O76: =O56*I43 -> 18087740
B77: Oil Growth % | G77: =(G76/F76)-1 -> 0.79867165 | H77: =(H76/G76)-1 -> 0.59313255 | I77: =(I76/H76)-1 -> 1.6972686 | J77: =(J76/I76)-1 -> 0.005304105 | K77: =(K76/J76)-1 -> 0.18741494 | L77: =(L76/K76)-1 -> 0.04 | M77: =(M76/L76)-1 -> 0.03 | N77: =(N76/M76)-1 -> 0.02 | O77: =(O76/N76)-1 -> 0.01
B79: NGL | F79: ='Historical Financials'!F11 -> 1053486 | G79: ='Historical Financials'!G11 -> 1733130 | H79: ='Historical Financials'!H11 -> 984418 | I79: ='Historical Financials'!I11 -> 1481958 | J79: ='Historical Financials'!J11 -> 1978860 | K79: =K59*E44 -> 2126250 | L79: =L59*F44 -> 2211300 | M79: =M59*G44 -> 2277639 | N79: =N59*H44 -> 2323191.8 | O79: =O59*I44 -> 2346423.7
B80: NGL Growth % | G80: =(G79/F79)-1 -> 0.64513814 | H80: =(H79/G79)-1 -> -0.43199991 | I80: =(I79/H79)-1 -> 0.50541538 | J80: =(J79/I79)-1 -> 0.335301 | K80: =(K79/J79)-1 -> 0.074482278 | L80: =(L79/K79)-1 -> 0.04 | M80: =(M79/L79)-1 -> 0.03 | N80: =(N79/M79)-1 -> 0.02 | O80: =(O79/N79)-1 -> 0.01
B82: Total Hydrocarbon Revenue | F82: =F79+F76+F73 -> 34538167 | G82: =G79+G76+G73 -> 61877197 | H82: =H79+H76+H73 -> 20939221 | I82: =I79+I76+I73 -> 25998712 | J82: =J79+J76+J73 -> 44903821 | K82: =K79+K76+K73 -> 55270425 | L82: =L79+L76+L73 -> 57481242 | M82: =M79+M76+M73 -> 59205679 | ... O82: =O79+O76+O73 -> 60993691
B83: Total Hydrocarbon Revenue Growth % | G83: =(G82/F82)-1 -> 0.79155996 | H83: =(H82/G82)-1 -> -0.66160036 | I83: =(I82/H82)-1 -> 0.24162747 | J83: =(J82/I82)-1 -> 0.7271556 | K83: =(K82/J82)-1 -> 0.2308624 | L83: =(L82/K82)-1 -> 0.04 | M83: =(M82/L82)-1 -> 0.03 | N83: =(N82/M82)-1 -> 0.02 | O83: =(O82/N82)-1 -> 0.01
B85: Gas Gathering System Revenue | F85: ='Historical Financials'!F13 -> 7865825 | G85: ='Historical Financials'!G13 -> 8085512 | H85: ='Historical Financials'!H13 -> 9790531 | I85: ='Historical Financials'!I13 -> 5524063 | J85: ='Historical Financials'!J13 -> 6683735 | K85: =J85*(1+K86) -> 7017921.8 | L85: =K85*(1+L86) -> 7368817.8 | M85: =L85*(1+M86) -> 7737258.7 | N85: =M85*(1+N86) -> 8124121.7 | O85: =N85*(1+O86) -> 8530327.7
B86: Gas Gathering System Revenue Growth % | G86: =(G85/F85)-1 -> 0.027929302 | H86: =(H85/G85)-1 -> 0.21087335 | I86: =(I85/H85)-1 -> -0.43577493 | J86: =(J85/I85)-1 -> 0.20993099 | K86: 0.05 | L86: =K86 -> 0.05 | M86: =L86 -> 0.05 | N86: =M86 -> 0.05 | O86: =N86 -> 0.05
B88: Total Revenue | F88: =F85+F82 -> 42403992 | G88: =G85+G82 -> 69962709 | H88: =H85+H82 -> 30729752 | I88: =I85+I82 -> 31522775 | J88: =J85+J82 -> 51587556 | K88: =K85+K82 -> 62288347 | L88: =L85+L82 -> 64850060 | M88: =M85+M82 -> 66942938 | ... O88: =O85+O82 -> 69524019
B89: Total Revenue Growth % | G89: =(G88/F88)-1 -> 0.64990855 | H89: =(H88/G88)-1 -> -0.56076955 | I89: =(I88/H88)-1 -> 0.025806359 | J89: =(J88/I88)-1 -> 0.63651696 | K89: =(K88/J88)-1 -> 0.20742969 | L89: =(L88/K88)-1 -> 0.041126683 | M89: =(M88/L88)-1 -> 0.032272571 | N89: =(N88/M88)-1 -> 0.023467397 | O89: =(O88/N88)-1 -> 0.014743049
B91: % of Revenue:
B92: Natural Gas % of Revnue | F92: =F73/F88 -> 0.74776415 | G92: =G73/G88 -> 0.81398698 | H92: =H73/H88 -> 0.48370758 | I92: =I73/I88 -> 0.34216746 | J92: =J73/J88 -> 0.56450525 | K92: =K73/K88 -> 0.590057 | L92: =L73/L88 -> 0.58941845 | M92: =M73/M88 -> 0.58812084 | ... O92: =O73/O88 -> 0.5833887
B93: Oil % of Revenue | F93: =F76/F88 -> 0.041894546 | G93: =G76/G88 -> 0.045671945 | H93: =H76/H88 -> 0.16565669 | I93: =I76/I88 -> 0.43557986 | J93: =J76/J88 -> 0.26757451 | K93: =K76/K88 -> 0.26313911 | L93: =L76/L88 -> 0.26285434 | M93: =M76/M88 -> 0.26227567 | ... O93: =O76/O88 -> 0.26016534
B94: NGL % of Revenue | F94: =F79/F88 -> 0.024844029 | G94: =G79/G88 -> 0.024772197 | H94: =H79/H88 -> 0.032034687 | I94: =I79/I88 -> 0.047012295 | J94: =J79/J88 -> 0.038359251 | K94: =K79/K88 -> 0.034135599 | L94: =L79/L88 -> 0.034098658 | M94: =M79/M88 -> 0.034023589 | ... O94: =O79/O88 -> 0.033749828
B95: Gas Gathering System % of Revenue | F95: =F85/F88 -> 0.18549728 | G95: =G85/G88 -> 0.11556888 | H95: =H85/H88 -> 0.31860104 | I95: =I85/I88 -> 0.17524038 | J95: =J85/J88 -> 0.12956099 | K95: =K85/K88 -> 0.11266829 | L95: =L85/L88 -> 0.11362854 | M95: =M85/M88 -> 0.11557991 | ... O95: =O85/O88 -> 0.12269613
B97: Commidity Prices:
B98: Natural Gas Price ($/Mcf) | F98: ='Production & Reserves'!F50 -> 3.0986206 | G98: ='Production & Reserves'!G50 -> 5.9927111 | H98: ='Production & Reserves'!H50 -> 1.7822799 | I98: ='Production & Reserves'!I50 -> 1.7561166 | J98: ='Production & Reserves'!J50 -> 2.9118534 | K98: =E42 -> 3.5 | L98: =F42 -> 3.5 | M98: =G42 -> 3.5 | N98: =H42 -> 3.5 | O98: =I42 -> 3.5
B99: Oil Price ($/Bbl) | F99: ='Production & Reserves'!F51 -> 71.05984 | G99: ='Production & Reserves'!G51 -> 99.854156 | H99: ='Production & Reserves'!H51 -> 78.316754 | I99: ='Production & Reserves'!I51 -> 73.426128 | J99: ='Production & Reserves'!J51 -> 61.89917 | K99: =E43 -> 70 | L99: =F43 -> 70 | M99: =G43 -> 70 | N99: =H43 -> 70 | O99: =I43 -> 70
B100: NGL Price ($/Bbl) | F100: ='Production & Reserves'!F52 -> 36.327103 | G100: ='Production & Reserves'!G52 -> 39.389318 | H100: ='Production & Reserves'!H52 -> 25.241487 | I100: ='Production & Reserves'!I52 -> 21.477652 | J100: ='Production & Reserves'!J52 -> 24.43037 | K100: =E44 -> 25 | L100: =F44 -> 25 | M100: =G44 -> 25 | N100: =H44 -> 25 | O100: =I44 -> 25
B102: Hydroocarbon Revenue / Boe | F102: =F82/F62 -> 19.629535 | G102: =G82/G62 -> 37.279163 | H102: =H82/H62 -> 14.015543 | I102: =I82/I62 -> 20.316785 | J102: =J82/J62 -> 22.78418 | K102: =K82/K62 -> 26.708753 | L102: =L82/L62 -> 26.708753 | M102: =M82/M62 -> 26.708753 | ... O102: =O82/O62 -> 26.708753
B105: Operating Expenses Forecast
F107: 2021 | G107: =F107+1 -> 2022 | H107: =G107+1 -> 2023 | I107: =H107+1 -> 2024 | J107: =I107+1 -> 2025 | K107: =J107+1 -> 2026 | L107: =K107+1 -> 2027 | M107: =L107+1 -> 2028 | N107: =M107+1 -> 2029 | O107: =N107+1 -> 2030
B109: Operating Expense:
B111: Lease Operating Expense | F111: ='Historical Financials'!F17 -> 7897738 | G111: ='Historical Financials'!G17 -> 7128631 | H111: ='Historical Financials'!H17 -> 6405281 | I111: ='Historical Financials'!I17 -> 7264824 | J111: ='Historical Financials'!J17 -> 12518325 | K111: =K112*K62 -> 13144241 | L111: =L112*L62 -> 13670011 | M111: =M112*M62 -> 14080111 | N111: =N112*N62 -> 14361713 | O111: =O112*O62 -> 14505331
B112: Lease Operating Expense / Boe | F112: =F111/F62 -> 4.4886263 | G112: =G111/G62 -> 4.2947872 | H112: =H111/H62 -> 4.2873367 | I112: =I111/I62 -> 5.6771222 | J112: =J111/J62 -> 6.3517928 | K112: =J112 -> 6.3517928 | L112: =K112 -> 6.3517928 | M112: =L112 -> 6.3517928 | N112: =M112 -> 6.3517928 | O112: =N112 -> 6.3517928
B114: Gathering System Operating Expense | F114: ='Historical Financials'!F18 -> 726646 | G114: ='Historical Financials'!G18 -> 2287763 | H114: ='Historical Financials'!H18 -> 2459694 | I114: ='Historical Financials'!I18 -> 2265190 | J114: ='Historical Financials'!J18 -> 2362036 | K114: =K115*K62 -> 3307434.5 | L114: =L115*L62 -> 3439731.9 | M114: =M115*M62 -> 3542923.8 | N114: =N115*N62 -> 3613782.3 | O114: =O115*O62 -> 3649920.1
B115: Gathering System Operating Expense / Boe | F115: =F114/F62 -> 0.41298437 | G115: =G114/G62 -> 1.3783089 | H115: =H114/H62 -> 1.6463815 | I115: =I114/I62 -> 1.7701407 | J115: =J114/J62 -> 1.1984961 | K115: =AVERAGE(G115:I115) -> 1.598277 | L115: =K115 -> 1.598277 | M115: =L115 -> 1.598277 | N115: =M115 -> 1.598277 | O115: =N115 -> 1.598277
B117: G&A Expense | F117: ='Historical Financials'!F27 -> 5875732 | G117: ='Historical Financials'!G27 -> 6325412 | H117: ='Historical Financials'!H27 -> 6293234 | I117: ='Historical Financials'!I27 -> 5688714 | J117: ='Historical Financials'!J27 -> 7168235 | K117: =K118*K62 -> 8332253.3 | L117: =L118*L62 -> 8665543.4 | M117: =M118*M62 -> 8925509.7 | N117: =N118*N62 -> 9104019.9 | O117: =O118*O62 -> 9195060.1
B118: G&A Expense / Boe | F118: =F117/F62 -> 3.3394328 | G118: =G117/G62 -> 3.8108718 | H118: =H117/H62 -> 4.2123387 | I118: =I117/I62 -> 4.4454655 | J118: =J117/J62 -> 3.6371594 | K118: =AVERAGE(G118:J118) -> 4.0264588 | L118: =K118 -> 4.0264588 | M118: =L118 -> 4.0264588 | N118: =M118 -> 4.0264588 | O118: =N118 -> 4.0264588
B120: DD&A Expense | F120: ='Historical Financials'!F20 -> 6627016 | G120: ='Historical Financials'!G20 -> 6438511 | H120: ='Historical Financials'!H20 -> 7685084 | I120: ='Historical Financials'!I20 -> 10185119 | J120: ='Historical Financials'!J20 -> 12170320 | K120: =K121*K62 -> 12778836 | L120: =L121*L62 -> 13289989 | M120: =M121*M62 -> 13688689 | N120: =N121*N62 -> 13962463 | O120: =O121*O62 -> 14102088
B121: DD&A Expense / Boe | F121: =F120/F62 -> 3.76642 | G121: =G120/G62 -> 3.8790105 | H121: =H120/H62 -> 5.1439652 | I121: =I120/I62 -> 7.9591969 | J121: =J120/J62 -> 6.1752152 | K121: =J121 -> 6.1752152 | L121: =K121 -> 6.1752152 | M121: =L121 -> 6.1752152 | N121: =M121 -> 6.1752152 | O121: =N121 -> 6.1752152
B123: Total Operating Expense | F123: =F111+F114+F117+F120 -> 21127132 | G123: =G111+G114+G117+G120 -> 22180317 | H123: =H111+H114+H117+H120 -> 22843293 | I123: =I111+I114+I117+I120 -> 25403847 | J123: =J111+J114+J117+J120 -> 34218916 | K123: =K111+K114+K117+K120 -> 37562765 | L123: =L111+L114+L117+L120 -> 39065276 | M123: =M111+M114+M117+M120 -> 40237234 | ... O123: =O111+O114+O117+O120 -> 41452398
B124: Total Operating Expense / Boe | F124: =F123/F62 -> 12.007463 | G124: =G123/G62 -> 13.362978 | H124: =H123/H62 -> 15.290022 | I124: =I123/I62 -> 19.851925 | J124: =J123/J62 -> 17.362664 | K124: =K123/K62 -> 18.151744 | L124: =L123/L62 -> 18.151744 | M124: =M123/M62 -> 18.151744 | ... O124: =O123/O62 -> 18.151744
B127: Profitability Forecast
F129: 2021 | G129: =F129+1 -> 2022 | H129: =G129+1 -> 2023 | I129: =H129+1 -> 2024 | J129: =I129+1 -> 2025 | K129: =J129+1 -> 2026 | L129: =K129+1 -> 2027 | M129: =L129+1 -> 2028 | N129: =M129+1 -> 2029 | O129: =N129+1 -> 2030
B132: EBTDAX | F132: =F88-F111-F114-F117 -> 27903876 | G132: =G88-G111-G114-G117 -> 54220903 | H132: =H88-H111-H114-H117 -> 15571543 | I132: =I88-I111-I114-I117 -> 16304047 | J132: =J88-J111-J114-J117 -> 29538960 | K132: =K88-K111-K114-K117 -> 37504418 | L132: =L88-L111-L114-L117 -> 39074774 | M132: =M88-M111-M114-M117 -> 40394393 | ... O132: =O88-O111-O114-O117 -> 42173708
B133: EBITDAX Margin % | F133: =F132/F88 -> 0.65804833 | G133: =G132/G88 -> 0.77499719 | H133: =H132/H88 -> 0.50672531 | I133: =I132/I88 -> 0.51721484 | J133: =J132/J88 -> 0.57259855 | K133: =K132/K88 -> 0.6021097 | L133: =L132/L88 -> 0.60254029 | M133: =M132/M88 -> 0.6034153 | ... O133: =O132/O88 -> 0.6066063
B134: EBITDAX / Boe | F134: =F132/F62 -> 15.85898 | G134: =G132/G62 -> 32.666474 | H134: =H132/H62 -> 10.42272 | I134: =I132/I62 -> 12.740855 | J134: =J132/J62 -> 14.988056 | K134: =K132/K62 -> 18.123548 | L134: =L132/L62 -> 18.156157 | M134: =M132/M62 -> 18.222641 | ... O134: =O132/O62 -> 18.467601
B136: Stock Based Compensation | F136: ='Historical Financials'!F26 -> 956084 | G136: ='Historical Financials'!G26 -> 1021026 | H136: ='Historical Financials'!H26 -> 1018262 | I136: ='Historical Financials'!I26 -> 1244416 | J136: ='Historical Financials'!J26 -> 1744917 | K136: =J136*(1+K137) -> 1919408.7 | L136: =K136*(1+L137) -> 2111349.6 | M136: =L136*(1+M137) -> 2322484.5 | N136: =M136*(1+N137) -> 2554733 | O136: =N136*(1+O137) -> 2810206.3
B137: Stock Based Compensation Growth % | G137: =(G136/F136)-1 -> 0.067924994 | H137: =(H136/G136)-1 -> -0.0027070809 | I137: =(I136/H136)-1 -> 0.22209805 | J137: =(J136/I136)-1 -> 0.4021975 | K137: 0.1 | L137: =K137 -> 0.1 | M137: =L137 -> 0.1 | N137: =M137 -> 0.1 | O137: =N137 -> 0.1
B139: EBITDA | F139: =F132-F136 -> 26947792 | G139: =G132-G136 -> 53199877 | H139: =H132-H136 -> 14553281 | I139: =I132-I136 -> 15059631 | J139: =J132-J136 -> 27794043 | K139: =K132-K136 -> 35585009 | L139: =L132-L136 -> 36963424 | M139: =M132-M136 -> 38071909 | ... O139: =O132-O136 -> 39363501
B140: EBITDA Margin % | F140: =F139/F88 -> 0.6355013 | G140: =G139/G88 -> 0.76040333 | H140: =H139/H88 -> 0.47358928 | I140: =I139/I88 -> 0.47773811 | J140: =J139/J88 -> 0.53877418 | K140: =K139/K88 -> 0.57129481 | L140: =L139/L88 -> 0.56998288 | M140: =M139/M88 -> 0.56872181 | ... O140: =O139/O88 -> 0.56618565
B142: DD&A Expense | F142: ='Historical Financials'!F20 -> 6627016 | G142: ='Historical Financials'!G20 -> 6438511 | H142: ='Historical Financials'!H20 -> 7685084 | I142: ='Historical Financials'!I20 -> 10185119 | J142: ='Historical Financials'!J20 -> 12170320 | K142: =K121*K62 -> 12778836 | L142: =L121*L62 -> 13289989 | M142: =M121*M62 -> 13688689 | N142: =N121*N62 -> 13962463 | O142: =O121*O62 -> 14102088
B143: DD&A Expense Growth % | G143: =(G142/F142)-1 -> -0.028444929 | H143: =(H142/G142)-1 -> 0.193612 | I143: =(I142/H142)-1 -> 0.32531004 | J143: =(J142/I142)-1 -> 0.19491191 | K143: =(K142/J142)-1 -> 0.05 | L143: =(L142/K142)-1 -> 0.04 | M143: =(M142/L142)-1 -> 0.03 | N143: =(N142/M142)-1 -> 0.02 | O143: =(O142/N142)-1 -> 0.01
B145: Operating Income (EBIT) | F145: =F139-F142 -> 20320776 | G145: =G139-G142 -> 46761366 | H145: =H139-H142 -> 6868197 | I145: =I139-I142 -> 4874512 | J145: =J139-J142 -> 15623723 | K145: =K139-K142 -> 22806173 | L145: =L139-L142 -> 23673435 | M145: =M139-M142 -> 24383220 | ... O145: =O139-O142 -> 25261414
B146: EBIT Margin % | F146: =F145/F88 -> 0.47921847 | G146: =G145/G88 -> 0.66837558 | H146: =H145/H88 -> 0.22350317 | I146: =I145/I88 -> 0.15463461 | J146: =J145/J88 -> 0.30285837 | K146: =K145/K88 -> 0.36613868 | L146: =L145/L88 -> 0.36504877 | M146: =M145/M88 -> 0.36423886 | ... O146: =O145/O88 -> 0.36334801
B148: Interest Expense | F148: =ABS('Historical Financials'!F39) -> 101382 | G148: =ABS('Historical Financials'!G39) -> 50782 | H148: =ABS('Historical Financials'!H39) -> 80379 | I148: =ABS('Historical Financials'!I39) -> 46400 | J148: =ABS('Historical Financials'!J39) -> 624160 | K148: =J148 -> 624160 | L148: =K148 -> 624160 | M148: =L148 -> 624160 | N148: =M148 -> 624160 | O148: =N148 -> 624160
B150: EBT | F150: =F145-F148 -> 20219394 | G150: =G145-G148 -> 46710584 | H150: =H145-H148 -> 6787818 | I150: =I145-I148 -> 4828112 | J150: =J145-J148 -> 14999563 | K150: =K145-K148 -> 22182013 | L150: =L145-L148 -> 23049275 | M150: =M145-M148 -> 23759060 | ... O150: =O145-O148 -> 24637254
B152: Income Tax Expense | F152: ='Historical Financials'!F45 -> 4440508 | G152: ='Historical Financials'!G45 -> 12157487 | H152: ='Historical Financials'!H45 -> 3200447 | I152: ='Historical Financials'!I45 -> 1629093 | J152: ='Historical Financials'!J45 -> 362731 | K152: =K150*K153 -> 4658222.7 | L152: =L150*L153 -> 4840347.7 | M152: =M150*M153 -> 4989402.5 | N152: =N150*N153 -> 5101539 | O152: =O150*O153 -> 5173823.3
...

Sheet Valuation
B2: NAV & Valuation
B5: Basic NAV Valuation
B7: Reserve Value (PV-10 Approximation) | F7: 210000000 | H7: Net Asset Value / Share | L7: =F13/F15 -> 5.5756279
B9: Cash & Cash Equivalents | F9: ='Capital Structure'!J26 -> 8465858 | H9: Current Share Price | L9: 5.28
B11: Total Debt | F11: ='Capital Structure'!E29 -> 45500000 | H11: Discount (Premium) to NAV | L11: =L7-L9 -> 0.29562792
B13: Net Asset Value (NAV) | F13: =F7+F9-F11 -> 172965858 | H13: Margin of Safety | L13: =(L7-L9)/L7 -> 0.053021457
B15: Diluted Shares Outstanding | F15: ='Capital Structure'!E16 -> 31021772
B18: Enterprise Value and Trading Multiples
B20: Year: | F20: 2026
B21: Share Price | F21: ='Capital Structure'!E7 -> 5.28 | H21: Free Cash Flow | L21: ='Forecast Model'!K177 -> 11528285
B22: Enterprise Value | F22: ='Capital Structure'!J34 -> 2.008291e+08 | H22: Free Cash Flow Yield | L22: =L21/F23 -> 0.070382418
B23: Market Capitalization | F23: ='Capital Structure'!J8 -> 1.6379496e+08
B24: Fully Diluted Shares | F24: ='Capital Structure'!E16 -> 31021772 | H24: Average Daily Production (Boe / Day) | L24: ='Forecast Model'!K62/365 -> 5669.5205
H25: EV / Boe per Day | L25: =F22/L24 -> 35422.589
B26: EBITDA | F26: ='Forecast Model'!K139 -> 35585009
B27: EBITDAX | F27: ='Forecast Model'!K132 -> 37504418 | H27: Proved Reserves (Boe) | L27: ='Production & Reserves'!J88 -> 26006333
B28: EBIT | F28: ='Forecast Model'!K150 -> 22182013 | H28: EV / Proved Boe | L28: =F22/L27 -> 7.722315
B30: EV / EBITDA | F30: =F22/F26 -> 5.6436433 | H30: NAV / Share | L30: =L7 -> 5.5756279
B31: EV / EBITDAX | F31: =F22/F27 -> 5.3548118 | H31: Price / NAV | L31: =F21/L30 -> 0.94697854
B32: EV / EBIT | F32: =F22/F28 -> 9.0536913
B34: EPS | F34: ='Forecast Model'!K159 -> 0.56488683
B35: Forward P / E | F35: =F21/F34 -> 9.347005
B38: Intrinsic Value and Margin of Safety
F40: Bear | G40: Base | H40: Bull
B42: Assumptions:
B43: Oil Price | F43: ='Forecast Model'!E28 -> 55 | G43: ='Forecast Model'!E29 -> 70 | H43: ='Forecast Model'!E30 -> 85
B44: Natural Gas Price | F44: ='Forecast Model'!E23 -> 2.5 | G44: ='Forecast Model'!E24 -> 3.5 | H44: ='Forecast Model'!E25 -> 5
B45: NGL Price | F45: ='Forecast Model'!E33 -> 18 | G45: ='Forecast Model'!E34 -> 25 | H45: ='Forecast Model'!E35 -> 35
B47: Forecasts (2026E):
B48: Production (Boe) | F48: ='Forecast Model'!C195 -> 1872291.7 | G48: ='Forecast Model'!C196 -> 2069375 | H48: ='Forecast Model'!C197 -> 2167916.7
B49: Revenue | F49: ='Forecast Model'!F195 -> 43807147 | G49: ='Forecast Model'!F196 -> 62288347 | H49: ='Forecast Model'!F197 -> 85992422
B50: EBITDAX | F50: ='Forecast Model'!C189 -> 21383592 | G50: ='Forecast Model'!C190 -> 37504418 | H50: ='Forecast Model'!C191 -> 60028306
B51: EBITDA | F51: ='Forecast Model'!F189 -> 19464183 | G51: ='Forecast Model'!F190 -> 35585009 | H51: ='Forecast Model'!F191 -> 58108897
B52: Target EV/EBITDAX | F52: 4.5 | G52: 5.5 | H52: 6.5
B54: Valuation:
B55: Target Enterprise Value | F55: =F50*F52 -> 96226164 | G55: =G50*G52 -> 2.062743e+08 | H55: =H50*H52 -> 3.9018399e+08
B56: Net Debt | F56: ='Capital Structure'!$J$28 -> 37034142 | G56: ='Capital Structure'!$J$28 -> 37034142 | H56: ='Capital Structure'!$J$28 -> 37034142
B57: Target Equity Value | F57: =F55-F56 -> 59192022 | G57: =G55-G56 -> 1.6924016e+08 | H57: =H55-H56 -> 3.5314984e+08
B58: Fully Diluted Share | F58: =('Capital Structure'!$E$16)+200000 -> 31221772 | G58: =('Capital Structure'!$E$16)+200000 -> 31221772 | H58: =('Capital Structure'!$E$16)+200000 -> 31221772
B59: Intrinsic Value / Share | F59: =F57/F58 -> 1.8958572 | G59: =G57/G58 -> 5.4205814 | H59: =H57/H58 -> 11.311012
B61: Market Comparisons:
B62: Current Share Price | F62: ='Capital Structure'!$E$7 -> 5.28 | G62: ='Capital Structure'!$E$7 -> 5.28 | H62: ='Capital Structure'!$E$7 -> 5.28
B63: Upside (Downside) | F63: =(F59-F62)/F62 -> -0.64093613 | G63: =(G59-G62)/G62 -> 0.026625259 | H63: =(H59-H62)/H62 -> 1.1422372
B64: Margin of Safety | F64: =MAX(0,(F59-F62)/F59) -> 0 | G64: =MAX(0,(G59-G62)/G59) -> 0.02593474 | H64: =MAX(0,(H59-H62)/H59) -> 0.53319828
