Workbook

Sheet Historical Financials
B2: Oddity Tech Ltd.
B3: By Deep Value Medici
B6: Income Statement
B9: In thousands | G9: 2021 | H9: 2022 | I9: 2023 | J9: =I9+1 -> 2024 | K9: =J9+1 -> 2025 | L9: Q1 2026 | M9: Q2 2026 | N9: H12026
B11: Revenue | G11: 222555 | H11: 324520 | I11: 508685 | J11: 647040 | K11: 809844 | L11: 197940 | M11: 180517 | N11: =SUM(L11:M11) -> 378457
B12: Cost of Revenue | G12: -69374 | H12: -106470 | I12: -150456 | J12: -178718 | K12: -221138 | L12: -59970 | M12: -56571 | N12: =SUM(L12:M12) -> -116541
B13: Gross Profit | G13: =SUM(G11:G12) -> 153181 | H13: =SUM(H11:H12) -> 218050 | I13: =SUM(I11:I12) -> 358229 | J13: =SUM(J11:J12) -> 468322 | K13: =SUM(K11:K12) -> 588706 | L13: =SUM(L11:L12) -> 137970 | M13: =SUM(M11:M12) -> 123946 | N13: =SUM(L13:M13) -> 261916
N14: =SUM(L14:M14) -> 0
B15: SG&A | G15: -133669 | H15: -190385 | I15: -283911 | J15: -352722 | K15: -469936 | L15: -163460 | M15: -125206 | N15: =SUM(L15:M15) -> -288666
B16: EBIT | G16: =G13+G15 -> 19512 | H16: =H13+H15 -> 27665 | I16: =I13+I15 -> 74318 | J16: =J13+J15 -> 115600 | K16: =K13+K15 -> 118770 | L16: =L13+L15 -> -25490 | M16: =M13+M15 -> -1260 | N16: =SUM(L16:M16) -> -26750
N17: =SUM(L17:M17) -> 0
B18: Depreciation | G18: 4006 | H18: 4408 | I18: 8605 | J18: 9827 | K18: 10687 | L18: 4269 | M18: =N18-L18 -> 3232 | N18: 7501
B19: EBITDA | G19: =G16+G18 -> 23518 | H19: =H16+H18 -> 32073 | I19: =I16+I18 -> 82923 | J19: =J16+J18 -> 125427 | K19: =K16+K18 -> 129457 | L19: =L16+L18 -> -21221 | M19: =M16+M18 -> 1972 | N19: =SUM(L19:M19) -> -19249
N20: =SUM(L20:M20) -> 0
B21: Financial Income, Net | G21: =-877 -> -877 | H21: 1247 | I21: 4283 | J21: 12306 | K21: 16935 | L21: 5306 | M21: 16533 | N21: =SUM(L21:M21) -> 21839
B22: EBT | G22: =G21+G16 -> 18635 | H22: =H21+H16 -> 28912 | I22: =I21+I16 -> 78601 | J22: =J21+J16 -> 127906 | K22: =K21+K16 -> 135705 | L22: =L21+L16 -> -20184 | M22: =M21+M16 -> 15273 | N22: =SUM(L22:M22) -> -4911
N23: =SUM(L23:M23) -> 0
B24: Taxes | G24: -4715 | H24: -7184 | I24: -20067 | J24: -26415 | K24: -24960 | L24: -1177 | M24: -2383 | N24: =SUM(L24:M24) -> -3560
B25: Net Income | G25: =G22+G24 -> 13920 | H25: =H22+H24 -> 21728 | I25: =I22+I24 -> 58534 | J25: =J22+J24 -> 101491 | K25: =K22+K24 -> 110745 | L25: =L22+L24 -> -21361 | M25: =M22+M24 -> 12890 | N25: =SUM(L25:M25) -> -8471
B28: Cash Flow Statement
B31: In thousands | G31: 2021 | H31: 2022 | I31: 2023 | J31: =I31+1 -> 2024 | K31: =J31+1 -> 2025
B33: Net Income | G33: =G25 -> 13920 | H33: =H25 -> 21728 | I33: =I25 -> 58534 | J33: =J25 -> 101491 | K33: =K25 -> 110745
B34: Depreciation & Amortization | G34: =G18 -> 4006 | H34: =H18 -> 4408 | I34: =I18 -> 8605 | J34: =J18 -> 9827 | K34: =K18 -> 10687
B35: Stock Based Comp | G35: 2107 | H35: 6697 | I35: 24111 | J35: 25022 | K35: 33891
B36: Change in Working Capital, net | G36: -9436 | H36: 8429 | I36: -2306 | J36: 6417 | K36: -66115
B37: Cash From Operations | G37: 10224 | H37: 39032 | I37: 87445 | J37: 137764 | K37: 87581
B39: Maintence Capex (PP&E) | G39: -2371 | H39: -2347 | I39: -2101 | J39: -3270 | K39: -3936
B40: Growth Capex (Software & Intangibles) | G40: -3354 | H40: -5051 | I40: -3705 | J40: -6332 | K40: -12250
B41: Acquisitions | G41: -11787 | H41: 0 | I41: -23173 | J41: 0 | K41: 0
B42: Treasury Investments, net | G42: 0 | H42: -18000 | I42: -110012 | J42: 11506 | K42: -250912
B43: Other Investing | G43: -1270 | H43: -382 | I43: -1000 | J43: -552 | K43: -150
B44: Cash From Investing | G44: =SUM(G39:G43) -> -18782 | H44: =SUM(H39:H43) -> -25780 | I44: =SUM(I39:I43) -> -139991 | J44: =SUM(J39:J43) -> 1352 | K44: =SUM(K39:K43) -> -267248
B46: Debt Issued (Repaid) | G46: -318 | H46: -362 | I46: -4313 | J46: 0 | K46: 582456
B47: Equity Issuance | G47: 0 | H47: 116 | I47: 54753 | J47: 18706 | K47: 12242
B48: Share Repurchases | G48: 0 | H48: 0 | I48: 0 | J48: -147283 | K48: 0
B49: Other Financing | G49: 0 | H49: 0 | I49: -1629 | J49: 1278 | K49: -63350
B50: Cash From Financing | G50: =SUM(G46:G49) -> -318 | H50: =SUM(H46:H49) -> -246 | I50: =SUM(I46:I49) -> 48811 | J50: =SUM(J46:J49) -> -127299 | K50: =SUM(K46:K49) -> 531348
B52: Ending Cash Balance | G52: 30889 | H52: 43114 | I52: 38766 | J52: 50347 | K52: 402279
B55: Balance Sheet
B58: In thousands | G58: 2021 | H58: 2022 | I58: 2023 | J58: =I58+1 -> 2024 | K58: =J58+1 -> 2025
B60: Cash & Equivalents | G60: X | H60: 40955 | I60: 36538 | J60: 50340 | K60: 402209
B61: Short-Term Deposits | G61: X | H61: 18000 | I61: 78000 | J61: 48000 | K61: 0
B62: Marketable Securities | G62: X | H62: 0 | I62: 1108 | J62: 1880 | K62: 11170
B63: Accounts Receivable | G63: X | H63: 7576 | I63: 9916 | J63: 9188 | K63: 16902
B64: Inventory | G64: X | H64: 70230 | I64: 84106 | J64: 99810 | K64: 135181
B65: Other Current Assets | G65: X | H65: 9172 | I65: 14144 | J65: 14151 | K65: 36336
B66: Total Current Assets | G66: X | H66: =SUM(H60:H65) -> 145933 | I66: =SUM(I60:I65) -> 223812 | J66: =SUM(J60:J65) -> 223369 | K66: =SUM(K60:K65) -> 601798
B68: Marketable Securities | G68: X | H68: 0 | I68: 50507 | J68: 68831 | K68: 362571
B69: PP&E | G69: X | H69: 9468 | I69: 9245 | J69: 9817 | K69: 10864
B70: Intangible Assets | G70: X | H70: 26800 | I70: 36001 | J70: 36458 | K70: 43582
B71: Goodwill | G71: X | H71: 16237 | I71: 64904 | J71: 64904 | K71: 64904
B72: Deferred Tax Assets | G72: X | H72: 2334 | I72: 3924 | J72: 8786 | K72: 27693
B73: Other Long-Term Assets | G73: X | H73: 15636 | I73: 16513 | J73: 26717 | K73: 26380
B74: Total Assets | G74: X | H74: =SUM(H66:H73) -> 216408 | I74: =SUM(I66:I73) -> 404906 | J74: =SUM(J66:J73) -> 438882 | K74: =SUM(K66:K73) -> 1137792
B76: Accounts Payable | G76: X | H76: 44807 | I76: 56185 | J76: 79130 | K76: 75957
B77: Accrued Liabilities | G77: X | H77: 37792 | I77: 49325 | J77: 38566 | K77: 32869
B78: Debt | G78: X | H78: 4565 | I78: 0 | J78: 0 | K78: 584368
B79: Lease Liabilities | G79: X | H79: 11966 | I79: 12514 | J79: 22710 | K79: 23465
B80: Other Liabilities | G80: X | H80: 6298 | I80: 3775 | J80: 16172 | K80: 24638
B81: Total Liabilities | G81: X | H81: =SUM(H76:H80) -> 105428 | I81: =SUM(I76:I80) -> 121799 | J81: =SUM(J76:J80) -> 156578 | K81: =SUM(K76:K80) -> 741297
B83: Additional Paid-In Capital | G83: X | H83: 53707 | I83: 178910 | J83: 76912 | K83: 77571
B84: Retained Earnings | G84: X | H84: 43244 | I84: 101778 | J84: 203269 | K84: 314014
B85: AOCI | G85: X | H85: 1738 | I85: 2402 | J85: 2106 | K85: 4892
B86: Total Equity | G86: X | H86: 98705 | I86: 283107 | J86: 282304 | K86: 396495
B88: Total Liabilities and Equity | G88: X | H88: =H81+H86 -> 204133 | I88: =I81+I86 -> 404906 | J88: =J81+J86 -> 438882 | K88: =K81+K86 -> 1137792

Sheet IS Analysis
B2: Oddity Tech Ltd.
B3: By Deep Value Medici
B6: Income Statement
B9: In thousands | G9: 2021 | H9: 2022 | I9: 2023 | J9: =I9+1 -> 2024 | K9: =J9+1 -> 2025 | L9: Q1 2026 | M9: Q2 2026 | N9: H12026
B11: Revenue | G11: 222555 | H11: 324520 | I11: 508685 | J11: 647040 | K11: 809844 | L11: 197940 | M11: 180517 | N11: =SUM(L11:M11) -> 378457
B12: Cost of Revenue | G12: -69374 | H12: -106470 | I12: -150456 | J12: -178718 | K12: -221138 | L12: -59970 | M12: -56571 | N12: =SUM(L12:M12) -> -116541
B13: Gross Profit | G13: =SUM(G11:G12) -> 153181 | H13: =SUM(H11:H12) -> 218050 | I13: =SUM(I11:I12) -> 358229 | J13: =SUM(J11:J12) -> 468322 | K13: =SUM(K11:K12) -> 588706 | L13: =SUM(L11:L12) -> 137970 | M13: =SUM(M11:M12) -> 123946 | N13: =SUM(L13:M13) -> 261916
B15: SG&A | G15: -133669 | H15: -190385 | I15: -283911 | J15: -352722 | K15: -469936 | L15: -163460 | M15: -125206 | N15: =SUM(L15:M15) -> -288666
B16: EBIT | G16: =G13+G15 -> 19512 | H16: =H13+H15 -> 27665 | I16: =I13+I15 -> 74318 | J16: =J13+J15 -> 115600 | K16: =K13+K15 -> 118770 | L16: =L13+L15 -> -25490 | M16: =M13+M15 -> -1260 | N16: =SUM(L16:M16) -> -26750
B18: Depreciation | G18: 4006 | H18: 4408 | I18: 8605 | J18: 9827 | K18: 10687 | L18: 4269 | M18: =N18-L18 -> 3232 | N18: 7501
B19: EBITDA | G19: =G16+G18 -> 23518 | H19: =H16+H18 -> 32073 | I19: =I16+I18 -> 82923 | J19: =J16+J18 -> 125427 | K19: =K16+K18 -> 129457 | L19: =L16+L18 -> -21221 | M19: =M16+M18 -> 1972 | N19: =SUM(L19:M19) -> -19249
B21: Financial Income, Net | G21: =-877 -> -877 | H21: 1247 | I21: 4283 | J21: 12306 | K21: 16935 | L21: 5306 | M21: 16533 | N21: =SUM(L21:M21) -> 21839
B22: EBT | G22: =G21+G16 -> 18635 | H22: =H21+H16 -> 28912 | I22: =I21+I16 -> 78601 | J22: =J21+J16 -> 127906 | K22: =K21+K16 -> 135705 | L22: =L21+L16 -> -20184 | M22: =M21+M16 -> 15273 | N22: =SUM(L22:M22) -> -4911
B24: Taxes | G24: -4715 | H24: -7184 | I24: -20067 | J24: -26415 | K24: -24960 | L24: -1177 | M24: -2383 | N24: =SUM(L24:M24) -> -3560
B25: Net Income | G25: =G22+G24 -> 13920 | H25: =H22+H24 -> 21728 | I25: =I22+I24 -> 58534 | J25: =J22+J24 -> 101491 | K25: =K22+K24 -> 110745 | L25: =L22+L24 -> -21361 | M25: =M22+M24 -> 12890 | N25: =SUM(L25:M25) -> -8471
B27: Other Relevant Costs:
B28: Advertising | G28: -63771 | H28: -92048 | I28: -125625 | J28: -164370 | K28: -245741
B31: Revenue, Margin, % of Revenue
G33: 2021 | H33: 2022 | I33: 2023 | J33: =I33+1 -> 2024 | K33: =J33+1 -> 2025 | L33: Q1 2026 | M33: Q2 2026 | N33: H12026
B35: Growth:
B36: Revenue | H36: =(H11-G11)/G11 -> 0.45815641 | I36: =(I11-H11)/H11 -> 0.56749969 | J36: =(J11-I11)/I11 -> 0.27198561 | K36: =(K11-J11)/J11 -> 0.2516135
B37: Gross Profit | H37: =(H13-G13)/G13 -> 0.42347941 | I37: =(I13-H13)/H13 -> 0.64287549 | J37: =(J13-I13)/I13 -> 0.30732576 | K37: =(K13-J13)/J13 -> 0.25705391
B38: EBIT | H38: =(H16-G16)/G16 -> 0.41784543 | I38: =(I16-H16)/H16 -> 1.6863546 | J38: =(J16-I16)/I16 -> 0.55547781 | K38: =(K16-J16)/J16 -> 0.027422145
B39: EBITDA | H39: =(H19-G19)/G19 -> 0.36376393 | I39: =(I19-H19)/H19 -> 1.5854457 | J39: =(J19-I19)/I19 -> 0.5125719 | K39: =(K19-J19)/J19 -> 0.032130243
B40: Net Income | H40: =(H25-G25)/G25 -> 0.56091954 | I40: =(I25-H25)/H25 -> 1.6939433 | J40: =(J25-I25)/I25 -> 0.73388116 | K40: =(K25-J25)/J25 -> 0.091180499
B42: Margins:
B43: Gross Margins | G43: =G13/G11 -> 0.6882838 | H43: =H13/H11 -> 0.67191544 | I43: =I13/I11 -> 0.7042256 | J43: =J13/J11 -> 0.72379142 | K43: =K13/K11 -> 0.72693753 | L43: =L13/L11 -> 0.6970294 | M43: =M13/M11 -> 0.68661677 | N43: =N13/N11 -> 0.69206277
B44: Operating Margin (EBIT Margin) | G44: =G16/G11 -> 0.08767271 | H44: =H16/H11 -> 0.085248983 | I44: =I16/I11 -> 0.14609827 | J44: =J16/J11 -> 0.17865974 | K44: =K16/K11 -> 0.14665787 | L44: =L16/L11 -> -0.1287764 | M44: =M16/M11 -> -0.006979952 | N44: =N16/N11 -> -0.070681742
B45: EBITDA Margin | G45: =G19/G11 -> 0.10567276 | H45: =H19/H11 -> 0.098832121 | I45: =I19/I11 -> 0.16301444 | J45: =J19/J11 -> 0.19384737 | K45: =K19/K11 -> 0.15985424 | L45: =L19/L11 -> -0.10720926 | M45: =M19/M11 -> 0.010924179 | N45: =N19/N11 -> -0.050861789
B47: % of Revenue
B48: Cost of Revenue | G48: =-G12/G11 -> 0.3117162 | H48: =-H12/H11 -> 0.32808456 | I48: =-I12/I11 -> 0.2957744 | J48: =-J12/J11 -> 0.27620858 | K48: =-K12/K11 -> 0.27306247 | L48: =-L12/L11 -> 0.3029706 | M48: =-M12/M11 -> 0.31338323 | N48: =-N12/N11 -> 0.30793723
B49: SG&A | G49: =-G15/G11 -> 0.60061108 | H49: =-H15/H11 -> 0.58666646 | I49: =-I15/I11 -> 0.55812733 | J49: =-J15/J11 -> 0.54513168 | K49: =-K15/K11 -> 0.58027966 | L49: =-L15/L11 -> 0.8258058 | M49: =-M15/M11 -> 0.69359672 | N49: =-N15/N11 -> 0.76274451
B50: Tax Rate | G50: =-G24/G22 -> 0.25301851 | H50: =-H24/H22 -> 0.24847814 | I50: =-I24/I22 -> 0.2553021 | J50: =-J24/J22 -> 0.20651885 | K50: =-K24/K22 -> 0.18392837 | L50: =-L24/L22 -> -0.058313516 | M50: =-M24/M22 -> 0.15602698 | N50: =-N24/N22 -> -0.72490328
B51: Advertising | G51: =G28/G11 -> -0.28654041 | H51: =H28/H11 -> -0.28364354 | I51: =I28/I11 -> -0.2469603 | J51: =J28/J11 -> -0.25403375 | K51: =K28/K11 -> -0.30344239 | L51: =L28/L11 -> 0 | M51: =M28/M11 -> 0 | N51: =N28/N11 -> 0
B55: Capex, FCF
G57: 2021 | H57: 2022 | I57: 2023 | J57: =I57+1 -> 2024 | K57: =J57+1 -> 2025 | L57: Q1 2026 | M57: Q2 2026 | N57: H12026
B59: Cash From Operations | G59: 10224 | H59: 39032 | I59: 87445 | J59: 137764 | K59: 87581
B60: Maintence Capex (PP&E) | G60: -2371 | H60: -2347 | I60: -2101 | J60: -3270 | K60: -3936
B61: Growth Capex (Software & Intangibles) | G61: -3354 | H61: -5051 | I61: -3705 | J61: -6332 | K61: -12250
B62: Free Cash Flow | G62: =SUM(G59:G60) -> 7853 | H62: =SUM(H59:H60) -> 36685 | I62: =SUM(I59:I60) -> 85344 | J62: =SUM(J59:J60) -> 134494 | K62: =SUM(K59:K60) -> 83645
B63: Owner FCF | G63: =SUM(G59:G61) -> 4499 | H63: =SUM(H59:H61) -> 31634 | I63: =SUM(I59:I61) -> 81639 | J63: =SUM(J59:J61) -> 128162 | K63: =SUM(K59:K61) -> 71395
B65: FCF Growth | H65: =(H62-G62)/G62 -> 3.6714631 | I65: =(I62-H62)/H62 -> 1.3264004 | J65: =(J62-I62)/I62 -> 0.57590457 | K65: =(K62-J62)/J62 -> -0.37807635
B67: Capex % of Revenue
B68: Maintence Capex (PP&E) | G68: =-G60/G11 -> 0.010653546 | H68: =-H60/H11 -> 0.0072322199 | I68: =-I60/I11 -> 0.0041302574 | J68: =-J60/J11 -> 0.0050537834 | K68: =-K60/K11 -> 0.0048601953
B69: Growth Capex (Software & Intangibles) | G69: =-G61/G11 -> 0.015070432 | H69: =-H61/H11 -> 0.015564526 | I69: =-I61/I11 -> 0.0072834859 | J69: =-J61/J11 -> 0.0097861029 | K69: =-K61/K11 -> 0.01512637
B72: Normalized Earnings & EPV
G74: 2025 | H74: Bear | I74: Base | J74: Bull | K74: V Bull
B76: Revenue | G76: =K11 -> 809844 | H76: =$G$76*(1+-0.35) -> 526398.6 | I76: =$G$76*(1+-0.3) -> 566890.8 | J76: =$G$76*(1+-0.25) -> 607383 | K76: =$G$76*(1+-0.2) -> 647875.2
B77: Gross Margin | G77: =K43 -> 0.72693753 | H77: 0.7 | I77: =H77 -> 0.7 | J77: =I77 -> 0.7 | K77: =J77 -> 0.7
B78: Gross Profit | G78: ='Historical Financials'!K13 -> 588706 | H78: =H76*H77 -> 368479.02 | I78: =I76*I77 -> 396823.56 | J78: =J76*J77 -> 425168.1 | K78: =K76*K77 -> 453512.64
B80: EBIT Margin | G80: =K44 -> 0.14665787 | H80: 0.1 | I80: =H80 -> 0.1 | J80: =I80 -> 0.1 | K80: =J80 -> 0.1
B81: Normalized EBIT | G81: =K16 -> 118770 | H81: =H76*H80 -> 52639.86 | I81: =I76*I80 -> 56689.08 | J81: =J76*J80 -> 60738.3 | K81: =K76*K80 -> 64787.52
B83: Tax Rate | G83: =K50 -> 0.18392837 | H83: 0.25 | I83: =H83 -> 0.25 | J83: =I83 -> 0.25 | K83: =J83 -> 0.25
B84: Normalized NOPAT | G84: =G81*(1-G83) -> 96924.827 | H84: =H81*(1-H83) -> 39479.895 | I84: =I81*(1-I83) -> 42516.81 | J84: =J81*(1-J83) -> 45553.725 | K84: =K81*(1-K83) -> 48590.64
B86: Capitalization Rate | G86: 0.1 | H86: 0.1 | I86: 0.1 | J86: 0.1 | K86: 0.1
B87: EPV Operations | G87: =G84/G86 -> 969248.27 | H87: =H84/H86 -> 394798.95 | I87: =I84/I86 -> 425168.1 | J87: =J84/J86 -> 455537.25 | K87: =K84/K86 -> 485906.4
B89: Liquid Assets | G89: ='BS Analysis '!K45 -> 775950 | H89: ='BS Analysis '!$L$45 -> 667336 | I89: ='BS Analysis '!$L$45 -> 667336 | J89: ='BS Analysis '!$L$45 -> 667336 | K89: ='BS Analysis '!$L$45 -> 667336
B90: Debt | G90: ='BS Analysis '!K24 -> 584368 | H90: ='BS Analysis '!$L$24 -> 585222 | I90: ='BS Analysis '!$L$24 -> 585222 | J90: ='BS Analysis '!$L$24 -> 585222 | K90: ='BS Analysis '!$L$24 -> 585222
B92: Equity Value | G92: =G87+G89-G90 -> 1160830.3 | H92: =H87+H89-H90 -> 476912.95 | I92: =I87+I89-I90 -> 507282.1 | J92: =J87+J89-J90 -> 537651.25 | K92: =K87+K89-K90 -> 568020.4
B94: Diluted Shares | G94: =56317 -> 56317 | H94: =56317 -> 56317 | I94: =56317 -> 56317 | J94: =56317 -> 56317 | K94: =56317 -> 56317
B95: Value per Share | G95: =G92/G94 -> 20.612431 | H95: =H92/H94 -> 8.4683657 | I95: =I92/I94 -> 9.0076194 | J95: =J92/J94 -> 9.5468731 | K95: =K92/K94 -> 10.086127
B98: EV/EBITDA & EV/EBIT
G100: 2025 | H100: Bear (-35%) | I100: Base (-30%) | J100: Bull (-25%) | K100: V Bull (-20%)
B102: Revenue | G102: =G76 -> 809844 | H102: =$G$76*(1+-0.35) -> 526398.6 | I102: =$G$76*(1+-0.3) -> 566890.8 | J102: =$G$76*(1+-0.25) -> 607383 | K102: =$G$76*(1+-0.2) -> 647875.2
B103: EBIT Margin | G103: =G80 -> 0.14665787 | H103: 0.1 | I103: 0.1 | J103: 0.1 | K103: 0.1
B104: EBIT | G104: =G102*G103 -> 118770 | H104: =H102*H103 -> 52639.86 | I104: =I102*I103 -> 56689.08 | J104: =J102*J103 -> 60738.3 | K104: =K102*K103 -> 64787.52
B106: D&A % of Revenue | G106: =K18/G102 -> 0.013196369 | H106: 0.015 | I106: 0.015 | J106: 0.015 | K106: 0.015
B107: D&A | G107: =K18 -> 10687 | H107: =H102*H106 -> 7895.979 | I107: =I102*I106 -> 8503.362 | J107: =J102*J106 -> 9110.745 | K107: =K102*K106 -> 9718.128
B108: EBITDA | G108: =G104+G107 -> 129457 | H108: =H104+H107 -> 60535.839 | I108: =I104+I107 -> 65192.442 | J108: =J104+J107 -> 69849.045 | K108: =K104+K107 -> 74505.648
B110: EV / EBIT | G110: =$D$118/G104 -> 5.0982283 | H110: =$D$118/H104 -> 11.503005 | I110: =$D$118/I104 -> 10.681362 | J110: =$D$118/J104 -> 9.969271 | K110: =$D$118/K104 -> 9.3461915
B111: EV / EBITDA | G111: =$D$118/G108 -> 4.6773567 | H111: =$D$118/H108 -> 10.002613 | I111: =$D$118/I108 -> 9.2881406 | J111: =$D$118/J108 -> 8.6689313 | K111: =$D$118/K108 -> 8.1271231
B113: EV Q1 26:
B114: Price | D114: 12.21
B115: Shares | D115: =G94 -> 56317
B116: Market Cap | D116: =D114*D115 -> 687630.57
B117: Net Debt (Cash) | D117: ='BS Analysis '!L52 -> -82114
B118: EV | D118: =D116+D117 -> 605516.57

Sheet Valuation and Scenario
B2: Income Statements
B4: In thousands | G4: 2021 | H4: 2022 | I4: 2023 | J4: =I4+1 -> 2024 | K4: =J4+1 -> 2025 | L4: Q1 2026 | M4: Q2 2026 | N4: H12026
B6: Revenue | G6: 222555 | H6: 324520 | I6: 508685 | J6: 647040 | K6: 809844 | L6: 197940 | M6: 180517 | N6: =SUM(L6:M6) -> 378457
B7: Cost of Revenue | G7: -69374 | H7: -106470 | I7: -150456 | J7: -178718 | K7: -221138 | L7: -59970 | M7: -56571 | N7: =SUM(L7:M7) -> -116541
B8: Gross Profit | G8: 153181 | H8: 218050 | I8: 358229 | J8: 468322 | K8: 588706 | L8: =SUM(L6:L7) -> 137970 | M8: =SUM(M6:M7) -> 123946 | N8: =SUM(N6:N7) -> 261916
B9: Profit Margin | G9: =G8/G6 -> 0.6882838 | H9: =H8/H6 -> 0.67191544 | I9: =I8/I6 -> 0.7042256 | J9: =J8/J6 -> 0.72379142 | K9: =K8/K6 -> 0.72693753 | L9: =L8/L6 -> 0.6970294 | M9: =M8/M6 -> 0.68661677 | N9: =N8/N6 -> 0.69206277
B11: SG&A | G11: -133669 | H11: -190385 | I11: -283911 | J11: -352722 | K11: -469936 | L11: -163460 | M11: -125206 | N11: =SUM(L11:M11) -> -288666
B12: EBIT | G12: 19512 | H12: 27665 | I12: 74318 | J12: 115600 | K12: 118770 | L12: =L8+L11 -> -25490 | M12: =M8+M11 -> -1260 | N12: =N8+N11 -> -26750
B13: Operating Margin | G13: =G12/G6 -> 0.08767271 | H13: =H12/H6 -> 0.085248983 | I13: =I12/I6 -> 0.14609827 | J13: =J12/J6 -> 0.17865974 | K13: =K12/K6 -> 0.14665787 | L13: =L12/L6 -> -0.1287764 | M13: =M12/M6 -> -0.006979952 | N13: =N12/N6 -> -0.070681742
B15: Depreciation | G15: 4006 | H15: 4408 | I15: 8605 | J15: 9827 | K15: 10687 | L15: 4269 | M15: 3232 | N15: 7501
B16: EBITDA | G16: 23518 | H16: 32073 | I16: 82923 | J16: 125427 | K16: 129457 | L16: =L12+L15 -> -21221 | M16: =M12+M15 -> 1972 | N16: =N12+N15 -> -19249
B17: EBITDA Margin | G17: =G16/G6 -> 0.10567276 | H17: =H16/H6 -> 0.098832121 | I17: =I16/I6 -> 0.16301444 | J17: =J16/J6 -> 0.19384737 | K17: =K16/K6 -> 0.15985424 | L17: =L16/L6 -> -0.10720926 | M17: =M16/M6 -> 0.010924179 | N17: =N16/N6 -> -0.050861789
B19: Other Relevant Costs:
B20: Advertising | G20: -63771 | H20: -92048 | I20: -125625 | J20: -164370 | K20: -245741 | L20: =L21*L11 -> -89903
B21: % of SG&A | G21: =G20/G11 -> 0.47708145 | H21: =H20/H11 -> 0.48348347 | I21: =I20/I11 -> 0.44248021 | J21: =J20/J11 -> 0.46600439 | K21: =K20/K11 -> 0.5229244 | L21: 0.55
B23: Financial Income, Net | G23: -877 | H23: 1247 | I23: 4283 | J23: 12306 | K23: 16935 | L23: 5306 | M23: 16533 | N23: 21839
B24: EBT | G24: 18635 | H24: 28912 | I24: 78601 | J24: 127906 | K24: 135705 | L24: =L12+L23 -> -20184 | M24: =M12+M23 -> 15273 | N24: =N12+N23 -> -4911
B26: Taxes | G26: -4715 | H26: -7184 | I26: -20067 | J26: -26415 | K26: -24960 | L26: -1177 | M26: -2383 | N26: -3560
B27: Net Income | G27: 13920 | H27: 21728 | I27: 58534 | J27: 101491 | K27: 110745 | L27: =L24+L26 -> -21361 | M27: =M24+M26 -> 12890 | N27: =N24+N26 -> -8471
B29: Other Relevant Costs:
B30: Advertising | G30: -63771 | H30: -92048 | I30: -125625 | J30: -164370 | K30: -245741 | L30: =L11*L31 -> -89903 | M30: =M11*M31 -> -68863.3 | N30: =N11*N31 -> -158766.3
B31: % of SG&A | G31: =G30/G11 -> 0.47708145 | H31: =H30/H11 -> 0.48348347 | I31: =I30/I11 -> 0.44248021 | J31: =J30/J11 -> 0.46600439 | K31: =K30/K11 -> 0.5229244 | L31: 0.55 | M31: 0.55 | N31: 0.55
B34: Advertising
B36: In thousands | G36: 2021 | H36: 2022 | I36: 2023 | J36: 2024 | K36: 2025 | L36: Q1 2026A
B38: Revenue | G38: 222555 | H38: 324520 | I38: 508685 | J38: 647040 | K38: 809844 | L38: 197940
B40: Other Relevant Costs:
B41: Advertising | G41: -63771 | H41: -92048 | I41: -125625 | J41: -164370 | K41: -245741 | L41: -89903
B42: % of SG&A | G42: 0.47708145 | H42: 0.48348347 | I42: 0.44248021 | J42: 0.46600439 | K42: 0.5229244 | L42: 0.55
B43: % of Revenue | G43: =-G41/G38 -> 0.28654041 | H43: =-H41/H38 -> 0.28364354 | I43: =-I41/I38 -> 0.2469603 | J43: =-J41/J38 -> 0.25403375 | K43: =-K41/K38 -> 0.30344239 | L43: =-L41/L38 -> 0.45419319
B46: 2028 Valuation w/ Different CAC Scenarios
B48: In thousands | G48: Delayed Fix | I48: Partial Normalization | K48: Full Normalization
B50: Revenue | G50: 550000 | I50: 650000 | K50: 700000
B51: Operating Margin | G51: 0.08 | I51: 0.13 | K51: 0.16
B52: EBIT | G52: =G50*G51 -> 44000 | I52: =I50*I51 -> 84500 | K52: =K50*K51 -> 112000
B54: EV / EBIT | G54: 10 | I54: 12.5 | K54: 12.5
B56: Enterprise Value | G56: =G52*G54 -> 440000 | I56: =I52*I54 -> 1056250 | K56: =K52*K54 -> 1400000
B57: Net Cash | G57: 0 | I57: 0 | K57: 0
B58: Equity Value | G58: =G56+G57 -> 440000 | I58: =I56+I57 -> 1056250 | K58: =K56+K57 -> 1400000
B60: Shares | G60: 56000 | I60: 56000 | K60: 56000
B61: Implied Price | G61: =G58/G60 -> 7.8571429 | I61: =I58/I60 -> 18.861607 | K61: =K58/K60 -> 25
B62: Return to $12.50 | G62: =(G61-12.5)/12.5 -> -0.37142857 | I62: =(I61-12.5)/12.5 -> 0.50892857 | K62: =(K61-12.5)/12.5 -> 1

Sheet BS Analysis 
B2: Balance Sheet
B4: In thousands | G4: 2021 | H4: 2022 | I4: 2023 | J4: =I4+1 -> 2024 | K4: =J4+1 -> 2025 | L4: Q1 2026 | M4: Q2 2026
B6: Cash & Equivalents | G6: X | H6: 40955 | I6: 36538 | J6: 50340 | K6: 402209 | L6: 278597 | M6: 167274
B7: Short-Term Deposits | G7: X | H7: 18000 | I7: 78000 | J7: 48000 | K7: 0 | N7: - Not all Securities Current Asset
B8: Marketable Securities | G8: X | H8: 0 | I8: 1108 | J8: 1880 | K8: 11170 | L8: 17113 | M8: 25880
B9: Accounts Receivable | G9: X | H9: 7576 | I9: 9916 | J9: 9188 | K9: 16902 | L9: 23313 | M9: 12129
B10: Inventory | G10: X | H10: 70230 | I10: 84106 | J10: 99810 | K10: 135181 | L10: 147976 | M10: 152170
B11: Other Current Assets | G11: X | H11: 9172 | I11: 14144 | J11: 14151 | K11: 36336 | L11: 33089 | M11: 33218
B12: Total Current Assets | G12: X | H12: =SUM(H6:H11) -> 145933 | I12: =SUM(I6:I11) -> 223812 | J12: =SUM(J6:J11) -> 223369 | K12: =SUM(K6:K11) -> 601798 | L12: =SUM(L6:L11) -> 500088 | M12: =SUM(M6:M11) -> 390671
B14: Marketable Securities | G14: X | H14: 0 | I14: 50507 | J14: 68831 | K14: 362571 | L14: 371626 | M14: 368008
B15: PP&E | G15: X | H15: 9468 | I15: 9245 | J15: 9817 | K15: 10864 | L15: 9986 | M15: 10044
B16: Intangible Assets | G16: X | H16: 26800 | I16: 36001 | J16: 36458 | K16: 43582 | L16: 46141 | M16: 48462
B17: Goodwill | G17: X | H17: 16237 | I17: 64904 | J17: 64904 | K17: 64904 | L17: 64904 | M17: 64904
B18: Deferred Tax Assets | G18: X | H18: 2334 | I18: 3924 | J18: 8786 | K18: 27693 | L18: 30299 | M18: 28811
B19: Other Long-Term Assets | G19: X | H19: 15636 | I19: 16513 | J19: 26717 | K19: 26380 | L19: =22701+4082 -> 26783 | M19: =19918+4305 -> 24223
B20: Total Assets | G20: X | H20: =SUM(H12:H19) -> 216408 | I20: =SUM(I12:I19) -> 404906 | J20: =SUM(J12:J19) -> 438882 | K20: =SUM(K12:K19) -> 1137792 | L20: =SUM(L12:L19) -> 1049827 | M20: =SUM(M12:M19) -> 935123
B22: Accounts Payable | G22: X | H22: 44807 | I22: 56185 | J22: 79130 | K22: 75957 | L22: 65252 | M22: 63076
B23: Accrued Liabilities | G23: X | H23: 37792 | I23: 49325 | J23: 38566 | K23: 32869 | L23: 51374 | M23: 44347
B24: Debt | G24: X | H24: 4565 | I24: 0 | J24: 0 | K24: 584368 | L24: 585222 | M24: 537246
B25: Lease Liabilities | G25: X | H25: 11966 | I25: 12514 | J25: 22710 | K25: 23465 | L25: =6537+17260 -> 23797 | M25: =5764+16231 -> 21995
B26: Other Liabilities | G26: X | H26: 6298 | I26: 3775 | J26: 16172 | K26: 24638 | L26: 25272 | M26: 25187
B27: Total Liabilities | G27: X | H27: =SUM(H22:H26) -> 105428 | I27: =SUM(I22:I26) -> 121799 | J27: =SUM(J22:J26) -> 156578 | K27: =SUM(K22:K26) -> 741297 | L27: =SUM(L22:L26) -> 750917 | M27: =SUM(M22:M26) -> 691851
B29: Additional Paid-In Capital | G29: X | H29: 53707 | I29: 178910 | J29: 76912 | K29: 77571 | L29: 4230 | M29: -65340
B30: Retained Earnings | G30: X | H30: 43244 | I30: 101778 | J30: 203269 | K30: 314014 | L30: 292653 | M30: 305543
B31: AOCI | G31: X | H31: 1738 | I31: 2402 | J31: 2106 | K31: 4892 | L31: 2011 | M31: 3055
B32: Total Equity | G32: X | H32: 98705 | I32: 283107 | J32: 282304 | K32: 396495 | L32: 298910 | M32: 243272
B34: Total Liabilities and Equity | G34: X | H34: =H27+H32 -> 204133 | I34: =I27+I32 -> 404906 | J34: =J27+J32 -> 438882 | K34: =K27+K32 -> 1137792 | L34: =L27+L32 -> 1049827 | M34: =M27+M32 -> 935123
B37: Liquidity
G39: 2021 | H39: 2022 | I39: 2023 | J39: =I39+1 -> 2024 | K39: =J39+1 -> 2025 | L39: Q1 2026 | M39: Q2 2026
B41: Cash | G41: X | H41: =H6 -> 40955 | I41: =I6 -> 36538 | J41: =J6 -> 50340 | K41: =K6 -> 402209 | L41: =L6 -> 278597 | M41: =M6 -> 167274
B42: Short-Term Deposits | G42: X | H42: =H7 -> 18000 | I42: =I7 -> 78000 | J42: =J7 -> 48000 | K42: =K7 -> 0 | L42: =L7 -> 0 | M42: =M7 -> 0
B43: Marketable Securities, short term | G43: =G6 -> X | H43: =H8 -> 0 | I43: =I8 -> 1108 | J43: =J8 -> 1880 | K43: =K8 -> 11170 | L43: =L8 -> 17113 | M43: =M8 -> 25880
B44: Marketable Securities, long term | G44: =G7 -> X | H44: =H14 -> 0 | I44: =I14 -> 50507 | J44: =J14 -> 68831 | K44: =K14 -> 362571 | L44: =L14 -> 371626 | M44: =M14 -> 368008
B45: Total Liquid Assets | G45: X | H45: =SUM(H41:H44) -> 58955 | I45: =SUM(I41:I44) -> 166153 | J45: =SUM(J41:J44) -> 169051 | K45: =SUM(K41:K44) -> 775950 | L45: =SUM(L41:L44) -> 667336 | M45: =SUM(M41:M44) -> 561162 | O45: =L45-M45 -> 106174
B47: Current Assets | G47: X | H47: =H12 -> 145933 | I47: =I12 -> 223812 | J47: =J12 -> 223369 | K47: =K12 -> 601798 | L47: =L12 -> 500088 | M47: =M12 -> 390671
B48: Current Liabilities | G48: X | H48: 90406 | I48: 109312 | J48: 124802 | K48: 114828 | L48: 123163 | M48: 113187
B49: Current Ratio | G49: X | H49: =H47/H48 -> 1.614196 | I49: =I47/I48 -> 2.0474605 | J49: =J47/J48 -> 1.789787 | K49: =K47/K48 -> 5.2408646 | L49: =L47/L48 -> 4.0603753 | M49: =M47/M48 -> 3.4515536
B51: Net Debt (Cash) | G51: X | H51: =H24-H6 -> -36390 | I51: =I24-I6 -> -36538 | J51: =J24-J6 -> -50340 | K51: =K24-K6 -> 182159 | L51: =L24-L6 -> 306625 | M51: =M24-M6 -> 369972
B52: Net Debt (Liquid Assets) | G52: X | H52: =H24-H45 -> -54390 | I52: =I24-I45 -> -166153 | J52: =J24-J45 -> -169051 | K52: =K24-K45 -> -191582 | L52: =L24-L45 -> -82114 | M52: =M24-M45 -> -23916
B55: Capital Structure
G57: 2021 | H57: 2022 | I57: 2023 | J57: =I57+1 -> 2024 | K57: =J57+1 -> 2025 | L57: Q1 2026 | M57: Q2 2026
B59: Total Debt | G59: =G24 -> X | H59: =H24 -> 4565 | I59: =I24 -> 0 | J59: =J24 -> 0 | K59: =K24 -> 584368 | L59: =L24 -> 585222 | M59: =M24 -> 537246
B60: EBITDA | G60: X | H60: ='Historical Financials'!H19 -> 32073 | I60: ='Historical Financials'!I19 -> 82923 | J60: ='Historical Financials'!J19 -> 125427 | K60: ='Historical Financials'!K19 -> 129457 | L60: ='Historical Financials'!L19 -> -21221 | M60: ='Historical Financials'!M19 -> 1972
B61: Debt / EBITDA | G61: X | H61: =H59/H60 -> 0.14233156 | I61: =I59/I60 -> 0 | J61: =J59/J60 -> 0 | K61: =K59/K60 -> 4.5139931 | L61: =L59/L60 -> -27.577494 | M61: =M59/M60 -> 272.43712 | N61: - under 3x is healthy position
B63: Net Debt (Cash) | G63: =G51 -> X | H63: =H51 -> -36390 | I63: =I51 -> -36538 | J63: =J51 -> -50340 | K63: =K51 -> 182159 | L63: =L51 -> 306625 | M63: =M51 -> 369972
B64: Net Debt (Liquid Assets) | G64: =G52 -> X | H64: =H52 -> -54390 | I64: =I52 -> -166153 | J64: =J52 -> -169051 | K64: =K52 -> -191582 | L64: =L52 -> -82114 | M64: =M52 -> -23916
B66: Debt / Equity | G66: X | H66: =H59/H32 -> 0.046248924 | I66: =I59/I32 -> 0 | J66: =J59/J32 -> 0 | K66: =K59/K32 -> 1.4738345 | L66: =L59/L32 -> 1.9578535 | M66: =M59/M32 -> 2.2084169
B69: Working Capital
G71: 2021 | H71: 2022 | I71: 2023 | J71: =I71+1 -> 2024 | K71: =J71+1 -> 2025 | L71: Q1 2026 | M71: Q2 2026
R72: =80/5.6 -> 14.285714
B73: Accounts Receivable | G73: X | H73: =H9 -> 7576 | I73: =I9 -> 9916 | J73: =J9 -> 9188 | K73: =K9 -> 16902 | L73: =L9 -> 23313 | M73: =M9 -> 12129
B74: Inventory | G74: X | H74: =H10 -> 70230 | I74: =I10 -> 84106 | J74: =J10 -> 99810 | K74: =K10 -> 135181 | L74: =L10 -> 147976 | M74: =M10 -> 152170
B75: Accounts Payable | G75: X | H75: =H22 -> 44807 | I75: =I22 -> 56185 | J75: =J22 -> 79130 | K75: =K22 -> 75957 | L75: =L22 -> 65252 | M75: =M22 -> 63076
B76: Net Working Capital | G76: X | H76: =H73+H74-H75 -> 32999 | I76: =I73+I74-I75 -> 37837 | J76: =J73+J74-J75 -> 29868 | K76: =K73+K74-K75 -> 76126 | L76: =L73+L74-L75 -> 106037 | M76: =M73+M74-M75 -> 101223
B78: % of Revenue:
B79: Revenue | H79: ='Historical Financials'!H11 -> 324520 | I79: ='Historical Financials'!I11 -> 508685 | J79: ='Historical Financials'!J11 -> 647040 | K79: ='Historical Financials'!K11 -> 809844 | L79: =K79*(1+-0.35) -> 526398.6 | M79: =L79*(1+-0.35) -> 342159.09
B80: Accounts Receivable | H80: =H73/H79 -> 0.023345248 | I80: =I73/I79 -> 0.0194934 | J80: =J73/J79 -> 0.014200049 | K80: =K73/K79 -> 0.020870686 | L80: =L73/L79 -> 0.044287732 | M80: =M73/M79 -> 0.035448423
B81: Inventory | H81: =H74/H79 -> 0.21641193 | I81: =I74/I79 -> 0.16534004 | J81: =J74/J79 -> 0.15425631 | K81: =K74/K79 -> 0.16692227 | L81: =L74/L79 -> 0.28111017 | M81: =M74/M79 -> 0.44473464
B82: Accounts Payable | H82: =H75/H79 -> 0.13807161 | I82: =I75/I79 -> 0.11045146 | J82: =J75/J79 -> 0.12229538 | K82: =K75/K79 -> 0.093792138 | L82: =L75/L79 -> 0.1239593 | M82: =M75/M79 -> 0.18434699
B83: Net Working Capital | H83: =H76/H79 -> 0.10168557 | I83: =I76/I79 -> 0.074381985 | J83: =J76/J79 -> 0.046160979 | K83: =K76/K79 -> 0.09400082 | L83: =L76/L79 -> 0.20143861 | M83: =M76/M79 -> 0.29583607
B85: Efficiency Ratios:
B86: Days Sales Outstanding | I86: =((I73+H73)/2)/I79*365 -> 6.2755733 | J86: =((J73+I73)/2)/J79*365 -> 5.3883531 | K86: =((K73+J73)/2)/K79*365 -> 5.8794348 | L86: =((L73+K73)/2)/L79*365 -> 13.942358 | M86: =((M73+L73)/2)/M79*365 -> 18.903969 | O86: Excellent (Direct to Consumer pay quickly)
B87: Days Inventory Outstanding | I87: =((I74+H74)/2)/I79*365 -> 55.370848 | J87: =((J74+I74)/2)/J79*365 -> 51.874181 | K87: =((K74+J74)/2)/K79*365 -> 52.955702 | L87: =((L74+K74)/2)/L79*365 -> 98.169244 | M87: =((M74+L74)/2)/M79*365 -> 160.09116 | O87: Very Stable. Inventory turning remains consistnent despite growth
B88: Days Payable Outstanding | I88: =((I75+H75)/2)/I79*365 -> 36.232718 | J88: =((J75+I75)/2)/J79*365 -> 38.166091 | K88: =((K75+J75)/2)/K79*365 -> 34.949172 | L88: =((L75+K75)/2)/L79*365 -> 48.956518 | M88: =((M75+L75)/2)/M79*365 -> 68.447283 | O88: Fairly consistent. Management not stretching suppliers to generate cash
B89: Cash Conversion Cycle | I89: =I86+I87-I88 -> 25.413704 | J89: =J86+J87-J88 -> 19.096443 | K89: =K86+K87-K88 -> 23.885964 | L89: =L86+L87-L88 -> 63.155083 | M89: =M86+M87-M88 -> 110.54784 | O89: Strong. Busines converts inventory to cash in about 20-25 days
B92: Returns on Capital
G94: 2021 | H94: 2022 | I94: 2023 | J94: =I94+1 -> 2024 | K94: =J94+1 -> 2025 | L94: Q1 2026 | M94: Q2 2026
B96: Operating NWC | G96: X | H96: =H9+H10+H11-H22-H23 -> 4379 | I96: =I9+I10+I11-I22-I23 -> 2656 | J96: =J9+J10+J11-J22-J23 -> 5453 | K96: =K9+K10+K11-K22-K23 -> 79593 | L96: =L9+L10+L11-L22-L23 -> 87752 | M96: =M9+M10+M11-M22-M23 -> 90094
B97: Invested Capital | G97: X | H97: =H96+H15+H16+H17 -> 56884 | I97: =I96+I15+I16+I17 -> 112806 | J97: =J96+J15+J16+J17 -> 116632 | K97: =K96+K15+K16+K17 -> 198943 | L97: =L96+L15+L16+L17 -> 208783 | M97: =M96+M15+M16+M17 -> 213504
B98: Average Invested Capital | G98: X | H98: X | I98: =(I97+H97)/2 -> 84845 | J98: =(J97+I97)/2 -> 114719 | K98: =(K97+J97)/2 -> 157787.5 | L98: =(L97+K97)/2 -> 203863 | M98: =(M97+L97)/2 -> 211143.5
B100: NOPAT | G100: X | H100: ='Historical Financials'!G16*(1-'IS Analysis'!G50) -> 14575.103 | I100: ='Historical Financials'!H16*(1-'IS Analysis'!H50) -> 20790.852 | J100: ='Historical Financials'!I16*(1-'IS Analysis'!I50) -> 55344.459 | K100: ='Historical Financials'!J16*(1-'IS Analysis'!J50) -> 91726.421 | L100: ='Historical Financials'!K16*(1-'IS Analysis'!K50) -> 96924.827 | M100: ='Historical Financials'!L16*(1-'IS Analysis'!L50) -> -26976.412
B101: Incremental NOPAT | G101: X | H101: X | I101: =(I100+H100)/2 -> 17682.978 | J101: =(J100+I100)/2 -> 38067.656 | K101: =(K100+J100)/2 -> 73535.44 | L101: =(L100+K100)/2 -> 94325.624 | M101: =(M100+L100)/2 -> 34974.208
B103: ROIC | G103: X | H103: =H100/H97 -> 0.256225 | I103: =I100/I97 -> 0.18430626 | J103: =J100/J97 -> 0.47452208 | K103: =K100/K97 -> 0.46106885 | L103: =L100/L97 -> 0.46423716 | M103: =M100/M97 -> -0.12635085
B104: Incremental ROIC | G104: X | H104: X | I104: =I101/I98 -> 0.20841508 | J104: =J101/J98 -> 0.33183392 | K104: =K101/K98 -> 0.46604097 | L104: =L101/L98 -> 0.46269124 | M104: =M101/M98 -> 0.16564189
B106: ROA | G106: X | H106: X | I106: ='Historical Financials'!I25/(('BS Analysis '!I20+'BS Analysis '!H20)/2) -> 0.18842003 | J106: ='Historical Financials'!J25/(('BS Analysis '!J20+'BS Analysis '!I20)/2) -> 0.24056043 | K106: ='Historical Financials'!K25/(('BS Analysis '!K20+'BS Analysis '!J20)/2) -> 0.14047926 | L106: ='Historical Financials'!L25/(('BS Analysis '!L20+'BS Analysis '!K20)/2) -> -0.019528995 | M106: ='Historical Financials'!M25/(('BS Analysis '!M20+'BS Analysis '!L20)/2) -> 0.012987733
B107: ROE | G107: X | H107: X | I107: ='Historical Financials'!I25/(('BS Analysis '!I32+'BS Analysis '!H32)/2) -> 0.30661163 | J107: ='Historical Financials'!J25/(('BS Analysis '!J32+'BS Analysis '!I32)/2) -> 0.35899903 | K107: ='Historical Financials'!K25/(('BS Analysis '!K32+'BS Analysis '!J32)/2) -> 0.32629689 | L107: ='Historical Financials'!L25/(('BS Analysis '!L32+'BS Analysis '!K32)/2) -> -0.061434704 | M107: ='Historical Financials'!M25/(('BS Analysis '!M32+'BS Analysis '!L32)/2) -> 0.047548609
B109: Asset Turnover | I109: ='Historical Financials'!I11/(('BS Analysis '!I20+'BS Analysis '!H20)/2) -> 1.637449 | J109: ='Historical Financials'!J11/(('BS Analysis '!J20+'BS Analysis '!I20)/2) -> 1.5336554 | K109: ='Historical Financials'!K11/(('BS Analysis '!K20+'BS Analysis '!J20)/2) -> 1.0272815 | L109: ='Historical Financials'!L11/(('BS Analysis '!L20+'BS Analysis '!K20)/2) -> 0.18096387 | M109: ='Historical Financials'!M11/(('BS Analysis '!M20+'BS Analysis '!L20)/2) -> 0.18188569
B112: Replacement Costs Estimates (Greenwald)
B116: In thousands | G116: 2026 | I116: % | K116: RC | M116: Equation
B118: Cash & Equivalents | G118: 278597 | I118: 1 | K118: =G118*I118 -> 278597 | M118: Total Assets | O118: =K132 -> 921865.95
B119: Short-Term Deposits | G119: 0 | I119: 1 | K119: =G119*I119 -> 0 | M119: Total Liabilities | O119: =K139 -> 750917
B120: Marketable Securities | G120: 17113 | I120: 1 | K120: =G120*I120 -> 17113 | M120: Equity | O120: =O118-O119 -> 170948.95
B121: Accounts Receivable | G121: 23313 | I121: 0.95 | K121: =G121*I121 -> 22147.35
B122: Inventory | G122: 147976 | I122: 0.8 | K122: =G122*I122 -> 118380.8 | M122: Shares | O122: 56317
B123: Other Current Assets | G123: 33089 | I123: 1 | K123: =G123*I123 -> 33089 | M123: RV per Share | O123: =O120/O122 -> 3.0354769
B124: Total Current Assets | G124: =SUM(G118:G123) -> 500088 | K124: =SUM(K118:K123) -> 469327.15
B126: Marketable Securities | G126: 371626 | I126: 1 | K126: =G126*I126 -> 371626
B127: PP&E | G127: 9986 | I127: 0.8 | K127: =G127*I127 -> 7988.8
B128: Intangible Assets | G128: 46141 | I128: 1 | K128: =G128*I128 -> 46141
B129: Goodwill | G129: 64904 | I129: 0 | K129: =G129*I129 -> 0
B130: Deferred Tax Assets | G130: 30299 | I130: 0 | K130: =G130*I130 -> 0
B131: Other Long-Term Assets | G131: =22701+4082 -> 26783 | I131: 1 | K131: =G131*I131 -> 26783
B132: Total Assets | G132: =SUM(G124:G131) -> 1049827 | K132: =SUM(K126:K131)+K124 -> 921865.95
B134: Accounts Payable | G134: 65252 | I134: 1 | K134: =G134*I134 -> 65252
B135: Accrued Liabilities | G135: 51374 | I135: 1 | K135: =G135*I135 -> 51374
B136: Debt | G136: 585222 | I136: 1 | K136: =G136*I136 -> 585222
B137: Lease Liabilities | G137: =6537+17260 -> 23797 | I137: 1 | K137: =G137*I137 -> 23797
B138: Other Liabilities | G138: 25272 | I138: 1 | K138: =G138*I138 -> 25272
B139: Total Liabilities | G139: =SUM(G134:G138) -> 750917 | K139: =SUM(K134:K138) -> 750917
B141: Additional Paid-In Capital | G141: 4230 | K141: =G141*I141 -> 0
...
